{"NKJV": {"1": "And I saw in the right <i>hand</i> of Him who sat on the throne a scroll written inside and on the back, sealed with seven seals.", "2": "Then I saw a strong angel proclaiming with a loud voice, “Who is worthy to open the scroll and to loose its seals?”", "3": "And no one in heaven or on the earth or under the earth was able to open the scroll, or to look at it.", "4": "So I wept much, because no one was found worthy to open and read the scroll, or to look at it.", "5": "But one of the elders said to me, “Do not weep. Behold, the Lion of the tribe of Judah, the Root of David, has prevailed to open the scroll and to loose its seven seals.”", "6": "And I looked, and behold, in the midst of the throne and of the four living creatures, and in the midst of the elders, stood a Lamb as though it had been slain, having seven horns and seven eyes, which are the seven Spirits of God sent out into all the earth.", "7": "Then He came and took the scroll out of the right hand of Him who sat on the throne.", "8": "Now when He had taken the scroll, the four living creatures and the twenty-four elders fell down before the Lamb, each having a harp, and golden bowls full of incense, which are the prayers of the saints.", "9": "And they sang a new song, saying:  “You are worthy to take the scroll, And to open its seals; For You were slain, And have redeemed us to God by Your blood Out of every tribe and tongue and people and nation,", "10": "And have made us kings and priests to our God; And we shall reign on the earth.”", "11": "Then I looked, and I heard the voice of many angels around the throne, the living creatures, and the elders; and the number of them was ten thousand times ten thousand, and thousands of thousands,", "12": "saying with a loud voice: “Worthy is the Lamb who was slain To receive power and riches and wisdom, And strength and honor and glory and blessing!”", "13": "And every creature which is in heaven and on the earth and under the earth and such as are in the sea, and all that are in them, I heard saying:  “Blessing and honor and glory and power <i>Be</i> to Him who sits on the throne, And to the Lamb, forever and ever!”", "14": "Then the four living creatures said, “Amen!” And the twenty-four elders fell down and worshiped Him who lives forever and ever."}, "KJV": {"1": "And<S>2532</S> I saw<S>1492</S> in<S>1909</S> the right hand<S>1188</S> of him that sat<S>2521</S> on<S>1909</S> the throne<S>2362</S> a book<S>975</S> written<S>1125</S> within<S>2081</S> and<S>2532</S> on the backside<S>3693</S>, sealed<S>2696</S> with seven<S>2033</S> seals<S>4973</S>.", "2": "And<S>2532</S> I saw<S>1492</S> a strong<S>2478</S> angel<S>32</S> proclaiming<S>2784</S> with a loud<S>3173</S> voice<S>5456</S>, Who<S>5101</S> is<S>2076</S> worthy<S>514</S> to open<S>455</S> the book<S>975</S>, and<S>2532</S> to loose<S>3089</S> the seals<S>4973</S> thereof<S>846</S>?", "3": "And<S>2532</S> no man<S>3762</S> in<S>1722</S> heaven<S>3772</S>, nor<S>3761</S> in<S>1909</S> earth<S>1093</S>, neither<S>3761</S> under<S>5270</S> the earth<S>1093</S>, was able<S>1410</S> to open<S>455</S> the book<S>975</S>, neither<S>3761</S> to look<S>991</S> thereon<S>846</S>.", "4": "And<S>2532</S> I<S>1473</S> wept<S>2799</S> much<S>4183</S>, because<S>3754</S> no man<S>3762</S> was found<S>2147</S> worthy<S>514</S> to open<S>455</S> and<S>2532</S> to read<S>314</S> the book<S>975</S>, neither<S>3777</S> to look<S>991</S> thereon<S>846</S>.", "5": "And<S>2532</S> one<S>1520</S> of<S>1537</S> the elders<S>4245</S> saith<S>3004</S> unto me<S>3427</S>, Weep<S>2799</S> not<S>3361</S>: behold<S>2400</S>, the Lion<S>3023</S> of<S>5607</S> <S>1537</S> the tribe<S>5443</S> of Juda<S>2455</S>, the Root<S>4491</S> of David<S>1138</S>, hath prevailed<S>3528</S> to open<S>455</S> the book<S>975</S>, and<S>2532</S> to loose<S>3089</S> the seven<S>2033</S> seals<S>4973</S> thereof<S>846</S>.", "6": "And<S>2532</S> I beheld<S>1492</S>, and<S>2532</S>, lo<S>2400</S>, in<S>1722</S> the midst<S>3319</S> of the throne<S>2362</S> and<S>2532</S> of the four<S>5064</S> beasts<S>2226</S>, and<S>2532</S> in<S>1722</S> the midst<S>3319</S> of the elders<S>4245</S>, stood<S>2476</S> a Lamb<S>721</S> as<S>5613</S> it had been slain<S>4969</S>, having<S>2192</S> seven<S>2033</S> horns<S>2768</S> and<S>2532</S> seven<S>2033</S> eyes<S>3788</S>, which<S>3739</S> are<S>1526</S> the seven<S>2033</S> Spirits<S>4151</S> of God<S>2316</S> sent forth<S>649</S> into<S>1519</S> all<S>3956</S> the earth<S>1093</S>.", "7": "And<S>2532</S> he came<S>2064</S> and<S>2532</S> took<S>2983</S> the book<S>975</S> out of<S>1537</S> the right hand<S>1188</S> of him that sat<S>2521</S> upon<S>1909</S> the throne<S>2362</S>.", "8": "And<S>2532</S> when<S>3753</S> he had taken<S>2983</S> the book<S>975</S>, the four<S>5064</S> beasts<S>2226</S> and<S>2532</S> four<S>5064</S> and twenty<S>1501</S> elders<S>4245</S> fell down<S>4098</S> before<S>1799</S> the Lamb<S>721</S>, having<S>2192</S> every one of them<S>1538</S> harps<S>2788</S>, and<S>2532</S> golden<S>5552</S> vials<S>5357</S> full<S>1073</S> of odours<S>2368</S>, which<S>3739</S> are<S>1526</S> the prayers<S>4335</S> of saints<S>40</S>. <sup>odours: or, incense</sup>", "9": "And<S>2532</S> they sung<S>103</S> a new<S>2537</S> song<S>5603</S>, saying<S>3004</S>, Thou art<S>1488</S> worthy<S>514</S> to take<S>2983</S> the book<S>975</S>, and<S>2532</S> to open<S>455</S> the seals<S>4973</S> thereof<S>846</S>: for<S>3754</S> thou wast slain<S>4969</S>, and<S>2532</S> hast redeemed<S>59</S> us<S>2248</S> to God<S>2316</S> by<S>1722</S> thy<S>4675</S> blood<S>129</S> out of<S>1537</S> every<S>3956</S> kindred<S>5443</S>, and<S>2532</S> tongue<S>1100</S>, and<S>2532</S> people<S>2992</S>, and<S>2532</S> nation<S>1484</S>;", "10": "And<S>2532</S> hast made<S>4160</S> us<S>2248</S> unto our<S>2257</S> God<S>2316</S> kings<S>935</S> and<S>2532</S> priests<S>2409</S>: and<S>2532</S> we shall reign<S>936</S> on<S>1909</S> the earth<S>1093</S>.", "11": "And<S>2532</S> I beheld<S>1492</S>, and<S>2532</S> I heard<S>191</S> the voice<S>5456</S> of many<S>4183</S> angels<S>32</S> round about<S>2943</S> the throne<S>2362</S> and<S>2532</S> the beasts<S>2226</S> and<S>2532</S> the elders<S>4245</S>: and<S>2532</S> the number<S>706</S> of them<S>846</S> was<S>2258</S> ten thousand<S>3461</S> times ten thousand<S>3461</S>, and<S>2532</S> thousands<S>5505</S> of thousands<S>5505</S>;", "12": "Saying<S>3004</S> with a loud<S>3173</S> voice<S>5456</S>, Worthy<S>514</S> is<S>2076</S> the Lamb<S>721</S> that was slain<S>4969</S> to receive<S>2983</S> power<S>1411</S>, and<S>2532</S> riches<S>4149</S>, and<S>2532</S> wisdom<S>4678</S>, and<S>2532</S> strength<S>2479</S>, and<S>2532</S> honour<S>5092</S>, and<S>2532</S> glory<S>1391</S>, and<S>2532</S> blessing<S>2129</S>.", "13": "And<S>2532</S> every<S>3956</S> creature<S>2938</S> which<S>3739</S> is<S>2076</S> in<S>1722</S> heaven<S>3772</S>, and<S>2532</S> on<S>1722</S> the earth<S>1093</S>, and<S>2532</S> under<S>5270</S> the earth<S>1093</S>, and<S>2532</S> such as<S>3739</S> are<S>2076</S> in<S>1909</S> the sea<S>2281</S>, and<S>2532</S> all<S>3956</S> that are in<S>1722</S> them<S>846</S>, heard I<S>191</S> saying<S>3004</S>, Blessing<S>2129</S>, and<S>2532</S> honour<S>5092</S>, and<S>2532</S> glory<S>1391</S>, and<S>2532</S> power<S>2904</S>, be unto him that sitteth<S>2521</S> upon<S>1909</S> the throne<S>2362</S>, and<S>2532</S> unto the Lamb<S>721</S> for<S>1519</S> ever<S>165</S> and ever<S>165</S>.", "14": "And<S>2532</S> the four<S>5064</S> beasts<S>2226</S> said<S>3004</S>, Amen<S>281</S>. And<S>2532</S> the four<S>5064</S> and twenty<S>1501</S> elders<S>4245</S> fell down<S>4098</S> and<S>2532</S> worshipped<S>4352</S> him that liveth<S>2198</S> for<S>1519</S> ever<S>165</S> and ever<S>165</S>."}, "ESV": {"1": "Then I saw in the right hand of him who was seated on the throne a scroll written within and on the back, sealed with seven seals.", "2": "And I saw a mighty angel proclaiming with a loud voice, “Who is worthy to open the scroll and break its seals?”", "3": "And no one in heaven or on earth or under the earth was able to open the scroll or to look into it,", "4": "and I began to weep loudly because no one was found worthy to open the scroll or to look into it.", "5": "And one of the elders said to me, “Weep no more; behold, the Lion of the tribe of Judah, the Root of David, has conquered, so that he can open the scroll and its seven seals.”", "6": "And between the throne and the four living creatures and among the elders I saw a Lamb standing, as though it had been slain, with seven horns and with seven eyes, which are the seven spirits of God sent out into all the earth.", "7": "And he went and took the scroll from the right hand of him who was seated on the throne.", "8": "And when he had taken the scroll, the four living creatures and the twenty-four elders fell down before the Lamb, each holding a harp, and golden bowls full of incense, which are the prayers of the saints.", "9": "And they sang a new song, saying, “Worthy are you to take the scroll and to open its seals, for you were slain, and by your blood you ransomed people for God from every tribe and language and people and nation,", "10": "and you have made them a kingdom and priests to our God, and they shall reign on the earth.”", "11": "Then I looked, and I heard around the throne and the living creatures and the elders the voice of many angels, numbering myriads of myriads and thousands of thousands,", "12": "saying with a loud voice, “Worthy is the Lamb who was slain, to receive power and wealth and wisdom and might and honor and glory and blessing!”", "13": "And I heard every creature in heaven and on earth and under the earth and in the sea, and all that is in them, saying, “To him who sits on the throne and to the Lamb be blessing and honor and glory and might forever and ever!”", "14": "And the four living creatures said, “Amen!” and the elders fell down and worshiped."}, "NASB": {"1": "I saw in the right hand of Him who sat on the throne a book written inside and on the back, sealed up with seven seals.", "2": "And I saw a strong angel proclaiming with a loud voice, 'Who is worthy to open the book and to break its seals?'", "3": "And no one in heaven or on the earth or under the earth was able to open the book or to look into it.", "4": "Then I [began] to weep greatly because no one was found worthy to open the book or to look into it;", "5": "and one of the elders said to me, 'Stop weeping; behold, the Lion that is from the tribe of Judah, the Root of David, has overcome so as to open the book and its seven seals.'", "6": "And I saw between the throne (with the four living creatures) and the elders a Lamb standing, as if slain, having seven horns and seven eyes, which are the seven Spirits of God, sent out into all the earth.", "7": "And He came and took the book out of the right hand of Him who sat on the throne.", "8": "When He had taken the book, the four living creatures and the twenty-four elders fell down before the Lamb, each one holding a harp and golden bowls full of incense, which are the prayers of the saints.", "9": "And they sang a new song, saying, 'Worthy are You to take the book and to break its seals; for You were slain, and purchased for God with Your blood [men] from every tribe and tongue and people and nation.", "10": "'You have made them [to be] a kingdom and priests to our God; and they will reign upon the earth.'", "11": "Then I looked, and I heard the voice of many angels around the throne and the living creatures and the elders; and the number of them was myriads of myriads, and thousands of thousands,", "12": "saying with a loud voice, 'Worthy is the Lamb that was slain to receive power and riches and wisdom and might and honor and glory and blessing.'", "13": "And every created thing which is in heaven and on the earth and under the earth and on the sea, and all things in them, I heard saying, 'To Him who sits on the throne, and to the Lamb, [be] blessing and honor and glory and dominion forever and ever.'", "14": "And the four living creatures kept saying, 'Amen.' And the elders fell down and worshiped."}, "NLT": {"1": "Then I saw a scroll in the right hand of the one who was sitting on the throne. There was writing on the inside and the outside of the scroll, and it was sealed with seven seals.", "2": "And I saw a strong angel, who shouted with a loud voice: “Who is worthy to break the seals on this scroll and open it?”", "3": "But no one in heaven or on earth or under the earth was able to open the scroll and read it.", "4": "Then I began to weep bitterly because no one was found worthy to open the scroll and read it.", "5": "But one of the twenty-four elders said to me, “Stop weeping! Look, the Lion of the tribe of Judah, the heir to David’s throne, has won the victory. He is worthy to open the scroll and its seven seals.”", "6": "Then I saw a Lamb that looked as if it had been slaughtered, but it was now standing between the throne and the four living beings and among the twenty-four elders. He had seven horns and seven eyes, which represent the sevenfold Spirit of God that is sent out into every part of the earth.", "7": "He stepped forward and took the scroll from the right hand of the one sitting on the throne.", "8": "And when he took the scroll, the four living beings and the twenty-four elders fell down before the Lamb. Each one had a harp, and they held gold bowls filled with incense, which are the prayers of God’s people.", "9": "And they sang a new song with these words: “You are worthy to take the scroll<br>and break its seals and open it.<br>For you were slaughtered, and your blood has ransomed people for God<br>from every tribe and language and people and nation.<br>", "10": "And you have caused them to become<br>a Kingdom of priests for our God.<br>And they will reign on the earth.”<br>", "11": "Then I looked again, and I heard the voices of thousands and millions of angels around the throne and of the living beings and the elders.", "12": "And they sang in a mighty chorus: “Worthy is the Lamb who was slaughtered —<br>to receive power and riches<br>and wisdom and strength<br>and honor and glory and blessing.”<br>", "13": "And then I heard every creature in heaven and on earth and under the earth and in the sea. They sang: “Blessing and honor and glory and power<br>belong to the one sitting on the throne<br>and to the Lamb forever and ever.”<br>", "14": "And the four living beings said, “Amen!” And the twenty-four elders fell down and worshiped the Lamb."}, "WEB": {"1": "I saw, in the right hand of him who sat on the throne, a book written inside and outside, sealed shut with seven seals.", "2": "I saw a mighty angel proclaiming with a loud voice, “Who is worthy to open the book, and to break its seals?”", "3": "No one in heaven above, or on the earth, or under the earth, was able to open the book, or to look in it.", "4": "And I wept much, because no one was found worthy to open the book, or to look in it.", "5": "One of the elders said to me, “Don’t weep. Behold, the Lion who is of the tribe of Judah, the Root of David, has overcome; he who opens the book and its seven seals.”", "6": "I saw in the middle of the throne and of the four living creatures, and in the middle of the elders, a Lamb standing, as though it had been slain, having seven horns, and seven eyes, which are the seven Spirits of God, sent out into all the earth.", "7": "Then he came, and he took it out of the right hand of him who sat on the throne.", "8": "Now when he had taken the book, the four living creatures and the twenty-four elders fell down before the Lamb, each one having a harp, and golden bowls full of incense, which are the prayers of the saints.", "9": "They sang a new song, saying, “You are worthy to take the book, and to open its seals: for you were killed, and bought us for God with your blood, out of every tribe, language, people, and nation, ", "10": "and made us kings and priests to our God, and we will reign on the earth.” ", "11": "I saw, and I heard something like a voice of many angels around the throne, the living creatures, and the elders; and the number of them was ten thousands of ten thousands, and thousands of thousands;", "12": "saying with a loud voice, “Worthy is the Lamb who has been killed to receive the power, wealth, wisdom, strength, honor, glory, and blessing!”", "13": "I heard every created thing which is in heaven, on the earth, under the earth, on the sea, and everything in them, saying, “To him who sits on the throne, and to the Lamb be the blessing, the honor, the glory, and the dominion, forever and ever! Amen!” ", "14": "The four living creatures said, “Amen!” The  elders fell down and worshiped. "}, "CSB17": {"1": "Then I saw in the right hand of the one seated on the throne a scroll with writing on both sides, sealed with seven seals. <sup>ⓙ</sup>", "2": "I also saw a mighty angel <sup>ⓚ</sup> proclaiming with a loud voice, “Who is worthy to open the scroll and break its seals?”", "3": "But no one in heaven or on earth or under the earth was able to open the scroll or even to look in it.", "4": "I wept and wept because no one was found worthy to open <sup>[1]</sup> the scroll or even to look in it.", "5": "Then one of the elders said to me, “Do not weep. Look, the Lion from the tribe of Judah, <sup>ⓛ</sup> the Root of David, <sup>ⓜ</sup> has conquered <sup>ⓝ</sup> so that he is able to open the scroll and <sup>[2]</sup> its seven seals.”", "6": "Then I saw one like a slaughtered lamb <sup>ⓐ</sup> standing in the midst of the throne and the four living creatures and among the elders. He had seven horns and seven eyes, which are the seven spirits of God <sup>ⓑ</sup> sent into all the earth.", "7": "He went and took the scroll out of the right hand of the one seated on the throne.", "8": "When he took the scroll, the four living creatures and the twenty-four elders fell down before the Lamb. Each one had a harp <sup>ⓒ</sup> and golden bowls <sup>ⓓ</sup> filled with incense, <sup>ⓔ</sup> which are the prayers of the saints.", "9": "And they sang a new song: <sup>ⓕ</sup> You are worthy to take the scroll <br>and to open its seals, <br>because you were slaughtered, <br>and you purchased <sup>[3]</sup> people <sup>[4]</sup> <br>for God by your blood <br>from every tribe and language <br>and people and nation. <sup>ⓖ</sup> <br>", "10": "You made them a kingdom <sup>[5]</sup> <br>and priests to our God, <sup>ⓗ</sup> <br>and they will reign on the earth. <br>", "11": "Then I looked and heard the voice of many angels around the throne, and also of the living creatures and of the elders. Their number was countless thousands, plus thousands of thousands. <sup>ⓘ</sup>", "12": "They said with a loud voice, Worthy is the Lamb who was slaughtered <br>to receive power and riches <br>and wisdom and strength <br>and honor and glory and blessing! <br>", "13": "I heard every creature in heaven, on earth, under the earth, <sup>ⓙ</sup> on the sea, and everything in them say, <sup>ⓚ</sup> Blessing and honor and glory and power <br>be to the one seated on the throne, <br>and to the Lamb, forever and ever! <br>", "14": "The four living creatures said, “Amen,” and the elders fell down and worshiped."}, "AMP": {"1": "I saw in the right hand of Him who was seated on the throne a scroll written on the inside and on the back, closed <i>and</i> sealed with seven seals.", "2": "And I saw a strong angel announcing with a loud voice, \"Who is worthy <i>[having the authority and virtue]</i> to open the scroll and to break its seals?\"", "3": "And no one in heaven or on earth or under the earth <i>[in Hades, the realm of the dead]</i> was able to open the scroll or look into it.", "4": "And I <i>began</i> to weep greatly because no one was found worthy to open the scroll or look into it.", "5": "Then one of the <i>[twenty-four]</i> elders said to me, \"Stop weeping! Look closely, the Lion of the tribe of Judah, the Root of David, has overcome <i>and</i> conquered! He can open the scroll and <i>[break]</i> its seven seals.\"", "6": "And there between the throne (with the four living creatures) and among the elders I saw a Lamb (Christ) standing, <i>[bearing scars and wounds]</i> as though it had been slain, with seven horns (complete power) and with seven eyes (complete knowledge), which are the seven Spirits of God who have been sent <i>[on duty]</i> into all the earth.", "7": "And He came and took the scroll from the right hand of Him who sat on the throne.", "8": "And when He had taken the scroll, the four living creatures and the twenty-four elders fell down before the Lamb (Christ), each one holding a harp and golden bowls full of fragrant incense, which are the prayers of the saints (God's people).", "9": "And they sang a new song <i>[of glorious redemption]</i>, saying, <br/>\"Worthy <i>and</i> deserving are You to take the scroll and to break its seals; for You were slain (sacrificed), and with Your blood You purchased <i>people</i> for God from every tribe and language and people and nation.<br/>", "10": "\"You have made them to be a kingdom <i>[of royal subjects]</i> and priests to our God; and they will reign on the earth.\"<br/>", "11": "Then I looked, and I heard the voice of many angels around the throne and <i>[the voice]</i> of the living creatures and the elders; and they numbered myriads of myriads, and thousands of thousands (innumerable),", "12": "saying in a loud voice, <br/>\"Worthy <i>and</i> deserving is the Lamb that was sacrificed to receive power and riches and wisdom and might and honor and glory and blessing.\"<br>", "13": "And I heard every created thing that is in heaven or on earth or under the earth <i>[in Hades, the realm of the dead]</i> or on the sea, and everything that is in them, saying <i>[together]</i>, <br/>\"To Him who sits on the throne, and to the Lamb (Christ), be blessing and honor and glory and dominion forever and ever.\"<br>", "14": "And the four living creatures kept saying, \"Amen.\" And the elders fell down and worshiped <i>[Him who lives forever and ever]</i>."}, "MSG": {"1": "I saw a scroll in the right hand of the One Seated on the Throne. It was written on both sides, fastened with seven seals.", "2": "I also saw a powerful Angel, calling out in a voice like thunder, \"Is there anyone who can open the scroll, who can break its seals?\"", "3": "There was no one—no one in Heaven, no one on earth, no one from the underworld—able to break open the scroll and read it.", "4": "I wept and wept and wept that no one was found able to open the scroll, able to read it.", "5": "One of the Elders said, \"Don't weep. Look—the Lion from Tribe Judah, the Root of David's Tree, has conquered. He can open the scroll, can rip through the seven seals.\"", "6": "So I looked, and there, surrounded by Throne, Animals, and Elders, was a Lamb, slaughtered but standing tall. Seven horns he had, and seven eyes, the Seven Spirits of God sent into all the earth.", "7": "He came to the One Seated on the Throne and took the scroll from his right hand.", "8": "The moment he took the scroll, the Four Animals and Twenty-four Elders fell down and worshiped the Lamb. Each had a harp and each had a bowl, a gold bowl filled with incense, the prayers of God's holy people.", "9": "And they sang a new song: Worthy! Take the scroll, open its seals. Slain! Paying in blood, you bought men and women, Bought them back from all over the earth, Bought them back for God.", "10": "Then you made them a Kingdom, Priests for our God, Priest-kings to rule over the earth.", "11": "I looked again. I heard a company of Angels around the Throne, the Animals, and the Elders—ten thousand times ten thousand their number, thousand after thousand after thousand", "12": "in full song: The slain Lamb is worthy! Take the power, the wealth, the wisdom, the strength! Take the honor, the glory, the blessing!", "13": "Then I heard every creature in Heaven and earth, in underworld and sea, join in, all voices in all places, singing: To the One on the Throne! To the Lamb! The blessing, the honor, the glory, the strength, For age after age after age.", "14": "The Four Animals called out, \"Oh, Yes!\" The Elders fell to their knees and worshiped."}, "NIV": {"1": "The Scroll and the Lamb<br/>Then I saw in the right hand of him who sat on the throne a scroll with writing on both sides and sealed with seven seals.", "2": "And I saw a mighty angel proclaiming in a loud voice, “Who is worthy to break the seals and open the scroll?”", "3": "But no one in heaven or on earth or under the earth could open the scroll or even look inside it.", "4": "I wept and wept because no one was found who was worthy to open the scroll or look inside.", "5": "Then one of the elders said to me, “Do not weep! See, the Lion of the tribe of Judah, the Root of David, has triumphed. He is able to open the scroll and its seven seals.”", "6": "Then I saw a Lamb, looking as if it had been slain, standing in the center of the throne, encircled by the four living creatures and the elders. He had seven horns and seven eyes, which are the seven spirits of God sent out into all the earth.", "7": "He came and took the scroll from the right hand of him who sat on the throne.", "8": "And when he had taken it, the four living creatures and the twenty-four elders fell down before the Lamb. Each one had a harp and they were holding golden bowls full of incense, which are the prayers of the saints.", "9": "And they sang a new song:<br/>“You are worthy to take the scroll<br/>and to open its seals,<br/>because you were slain,<br/>and with your blood you purchased men for God<br/>from every tribe and language and people and nation.", "10": "You have made them to be a kingdom and priests to serve our God,<br/>and they will reign on the earth.”", "11": "Then I looked and heard the voice of many angels, numbering thousands upon thousands, and ten thousand times ten thousand. They encircled the throne and the living creatures and the elders.", "12": "In a loud voice they sang:<br/>“Worthy is the Lamb, who was slain,<br/>to receive power and wealth and wisdom and strength<br/>and honor and glory and praise!”", "13": "Then I heard every creature in heaven and on earth and under the earth and on the sea, and all that is in them, singing:<br/>“To him who sits on the throne and to the Lamb<br/>be praise and honor and glory and power,<br/>for ever and ever!”", "14": "The four living creatures said, “Amen,” and the elders fell down and worshiped."}, "NRSVCE": {"1": "Then I saw in the right hand of the one seated on the throne a scroll written on the inside and on the back, sealed with seven seals;", "2": "and I saw a mighty angel proclaiming with a loud voice, “Who is worthy to open the scroll and break its seals?”", "3": "And no one in heaven or on earth or under the earth was able to open the scroll or to look into it.", "4": "And I began to weep bitterly because no one was found worthy to open the scroll or to look into it.", "5": "Then one of the elders said to me, “Do not weep. See, the Lion of the tribe of Judah, the Root of David, has conquered, so that he can open the scroll and its seven seals.”", "6": "Then I saw between the throne and the four living creatures and among the elders a Lamb standing as if it had been slaughtered, having seven horns and seven eyes, which are the seven spirits of God sent out into all the earth.", "7": "He went and took the scroll from the right hand of the one who was seated on the throne.", "8": "When he had taken the scroll, the four living creatures and the twenty-four elders fell before the Lamb, each holding a harp and golden bowls full of incense, which are the prayers of the saints.", "9": "They sing a new song: “You are worthy to take the scroll <br>and to open its seals, <br>for you were slaughtered and by your blood you ransomed for God <br>saints from every tribe and language and people and nation;<br>", "10": "you have made them to be a kingdom and priests serving our God, <br>and they will reign on earth.” <br>", "11": "Then I looked, and I heard the voice of many angels surrounding the throne and the living creatures and the elders; they numbered myriads of myriads and thousands of thousands,", "12": "singing with full voice, “Worthy is the Lamb that was slaughtered <br>to receive power and wealth and wisdom and might <br>and honor and glory and blessing!” <br>", "13": "Then I heard every creature in heaven and on earth and under the earth and in the sea, and all that is in them, singing, “To the one seated on the throne and to the Lamb <br>be blessing and honor and glory and might <br>forever and ever!” <br>", "14": "And the four living creatures said, “Amen!” And the elders fell down and worshiped."}, "NET": {"1": "Then I saw in the right hand of the one who was seated on the throne a scroll written on the front and back and sealed with seven seals.", "2": "And I saw a powerful angel proclaiming in a loud voice: “Who is worthy to open the scroll and to break its seals?”", "3": "But no one in heaven or on earth or under the earth was able to open the scroll or look into it.", "4": "So I began weeping bitterly because no one was found who was worthy to open the scroll or to look into it.", "5": "Then one of the elders said to me, “Stop weeping! Look, the Lion of the tribe of Judah, the root of David, has conquered; thus he can open the scroll and its seven seals.”", "6": "Then I saw standing in the middle of the throne and of the four living creatures, and in the middle of the elders, a Lamb that appeared to have been killed. He had seven horns and seven eyes, which are the seven spirits of God sent out into all the earth.", "7": "Then he came and took the scroll from the right hand of the one who was seated on the throne,", "8": "and when he had taken the scroll, the four living creatures and the twenty-four elders threw themselves to the ground before the Lamb. Each of them had a harp and golden bowls full of incense (which are the prayers of the saints).", "9": "They were singing a new song: “You are worthy to take the scroll and to open its seals because you were killed, and at the cost of your own blood you have purchased for God persons from every tribe, language, people, and nation.", "10": "You have appointed them as a kingdom and priests to serve our God, and they will reign on the earth.”", "11": "Then I looked and heard the voice of many angels in a circle around the throne, as well as the living creatures and the elders. Their number was ten thousand times ten thousand — thousands times thousands —", "12": "all of whom were singing in a loud voice: “Worthy is the lamb who was killed to receive power and wealth and wisdom and might and honor and glory and praise!”", "13": "Then I heard every creature — in heaven, on earth, under the earth, in the sea, and all that is in them — singing: “To the one seated on the throne and to the Lamb be praise, honor, glory, and ruling power forever and ever!”", "14": "And the four living creatures were saying “Amen,” and the elders threw themselves to the ground and worshiped."}}