[
  {
    "strongs": "G1063",
    "transliteration": "gar",
    "gloss": "for, because, indeed",
    "original": "γάρ",
    "lang": "greek",
    "file": "G1063.html"
  },
  {
    "strongs": "G1067",
    "transliteration": "geenna",
    "gloss": "Gehenna, hell, the place of final punishment",
    "original": "γέεννα",
    "lang": "greek",
    "file": "G1067.html"
  },
  {
    "strongs": "G1080",
    "transliteration": "gennaō",
    "gloss": "To beget, give birth to, produce",
    "original": "γεννάω",
    "lang": "greek",
    "file": "G1080.html"
  },
  {
    "strongs": "G1096",
    "transliteration": "ginomai",
    "gloss": "to become, to come into being, to happen",
    "original": "γίνομαι",
    "lang": "greek",
    "file": "G1096.html"
  },
  {
    "strongs": "G1097",
    "transliteration": "ginōskō",
    "gloss": "to know, to come to know, to recognize",
    "original": "γινώσκω",
    "lang": "greek",
    "file": "G1097.html"
  },
  {
    "strongs": "G1100",
    "transliteration": "glōssa",
    "gloss": "Tongue, language",
    "original": "γλῶσσα",
    "lang": "greek",
    "file": "G1100.html"
  },
  {
    "strongs": "G1125",
    "transliteration": "graphō",
    "gloss": "to write, it is written",
    "original": "γράφω",
    "lang": "greek",
    "file": "G1125.html"
  },
  {
    "strongs": "G1135",
    "transliteration": "gynē",
    "gloss": "Woman, wife",
    "original": "γυνή",
    "lang": "greek",
    "file": "G1135.html"
  },
  {
    "strongs": "G1209",
    "transliteration": "dechomai",
    "gloss": "To receive, accept, welcome",
    "original": "δέχομαι",
    "lang": "greek",
    "file": "G1209.html"
  },
  {
    "strongs": "G1228",
    "transliteration": "diabolos",
    "gloss": "devil, slanderer, accuser",
    "original": "διάβολος",
    "lang": "greek",
    "file": "G1228.html"
  },
  {
    "strongs": "G1242",
    "transliteration": "diathēkē",
    "gloss": "Covenant, testament, will",
    "original": "διαθήκη",
    "lang": "greek",
    "file": "G1242.html"
  },
  {
    "strongs": "G1247",
    "transliteration": "diakoneō",
    "gloss": "to serve, to minister, to wait on",
    "original": "διακονέω",
    "lang": "greek",
    "file": "G1247.html"
  },
  {
    "strongs": "G1271",
    "transliteration": "dianoia",
    "gloss": "mind, understanding, thought",
    "original": "διάνοια",
    "lang": "greek",
    "file": "G1271.html"
  },
  {
    "strongs": "G129",
    "transliteration": "haima",
    "gloss": "blood",
    "original": "αἷμα",
    "lang": "greek",
    "file": "G129.html"
  },
  {
    "strongs": "G1320",
    "transliteration": "didaskalos",
    "gloss": "teacher, master, instructor",
    "original": "διδάσκαλος",
    "lang": "greek",
    "file": "G1320.html"
  },
  {
    "strongs": "G1321",
    "transliteration": "didaskō",
    "gloss": "to teach, to instruct",
    "original": "διδάσκω",
    "lang": "greek",
    "file": "G1321.html"
  },
  {
    "strongs": "G1325",
    "transliteration": "didōmi",
    "gloss": "To give, grant, bestow",
    "original": "δίδωμι",
    "lang": "greek",
    "file": "G1325.html"
  },
  {
    "strongs": "G1342",
    "transliteration": "dikaios",
    "gloss": "righteous, just, upright",
    "original": "δίκαιος",
    "lang": "greek",
    "file": "G1342.html"
  },
  {
    "strongs": "G1343",
    "transliteration": "dikaiosynē",
    "gloss": "righteousness, justice",
    "original": "δικαιοσύνη",
    "lang": "greek",
    "file": "G1343.html"
  },
  {
    "strongs": "G1380",
    "transliteration": "dokeō",
    "gloss": "to think, to seem, to suppose",
    "original": "δοκέω",
    "lang": "greek",
    "file": "G1380.html"
  },
  {
    "strongs": "G1381",
    "transliteration": "dokimazō",
    "gloss": "To test, prove, examine, approve",
    "original": "δοκιμάζω",
    "lang": "greek",
    "file": "G1381.html"
  },
  {
    "strongs": "G1391",
    "transliteration": "doxa",
    "gloss": "glory, honor, splendor",
    "original": "δόξα",
    "lang": "greek",
    "file": "G1391.html"
  },
  {
    "strongs": "G1401",
    "transliteration": "doulos",
    "gloss": "slave, servant, bondservant",
    "original": "δοῦλος",
    "lang": "greek",
    "file": "G1401.html"
  },
  {
    "strongs": "G1410",
    "transliteration": "dynamai",
    "gloss": "To be able, have power",
    "original": "δύναμαι",
    "lang": "greek",
    "file": "G1410.html"
  },
  {
    "strongs": "G1411",
    "transliteration": "dynamis",
    "gloss": "power, might, miracle",
    "original": "δύναμις",
    "lang": "greek",
    "file": "G1411.html"
  },
  {
    "strongs": "G142",
    "transliteration": "airō",
    "gloss": "To take up, lift, carry away, remove",
    "original": "αἴρω",
    "lang": "greek",
    "file": "G142.html"
  },
  {
    "strongs": "G1453",
    "transliteration": "egeirō",
    "gloss": "to raise, to awaken, to rise",
    "original": "ἐγείρω",
    "lang": "greek",
    "file": "G1453.html"
  },
  {
    "strongs": "G1484",
    "transliteration": "ethnos",
    "gloss": "Nation, people, Gentiles",
    "original": "ἔθνος",
    "lang": "greek",
    "file": "G1484.html"
  },
  {
    "strongs": "G1492",
    "transliteration": "eidō",
    "gloss": "To see, know, perceive, understand",
    "original": "εἴδω",
    "lang": "greek",
    "file": "G1492.html"
  },
  {
    "strongs": "G1515",
    "transliteration": "eirēnē",
    "gloss": "Peace, harmony, tranquility",
    "original": "εἰρήνη",
    "lang": "greek",
    "file": "G1515.html"
  },
  {
    "strongs": "G154",
    "transliteration": "aiteō",
    "gloss": "To ask, request, demand",
    "original": "αἰτέω",
    "lang": "greek",
    "file": "G154.html"
  },
  {
    "strongs": "G1577",
    "transliteration": "ekklēsia",
    "gloss": "church, assembly, congregation",
    "original": "ἐκκλησία",
    "lang": "greek",
    "file": "G1577.html"
  },
  {
    "strongs": "G1588",
    "transliteration": "eklektos",
    "gloss": "Chosen, select, elect",
    "original": "ἐκλεκτός",
    "lang": "greek",
    "file": "G1588.html"
  },
  {
    "strongs": "G165",
    "transliteration": "aiōn",
    "gloss": "age, era, eternity",
    "original": "αἰών",
    "lang": "greek",
    "file": "G165.html"
  },
  {
    "strongs": "G1650",
    "transliteration": "elegchos",
    "gloss": "proof, conviction, evidence",
    "original": "ἔλεγχος",
    "lang": "greek",
    "file": "G1650.html"
  },
  {
    "strongs": "G1656",
    "transliteration": "eleos",
    "gloss": "mercy, compassion, pity",
    "original": "ἔλεος",
    "lang": "greek",
    "file": "G1656.html"
  },
  {
    "strongs": "G166",
    "transliteration": "aiōnios",
    "gloss": "eternal, everlasting, age-long",
    "original": "αἰώνιος",
    "lang": "greek",
    "file": "G166.html"
  },
  {
    "strongs": "G1680",
    "transliteration": "elpis",
    "gloss": "hope, expectation",
    "original": "ἐλπίς",
    "lang": "greek",
    "file": "G1680.html"
  },
  {
    "strongs": "G1699",
    "transliteration": "Emos",
    "gloss": "My, mine",
    "original": "ἐμός",
    "lang": "greek",
    "file": "G1699.html"
  },
  {
    "strongs": "G1722",
    "transliteration": "en",
    "gloss": "In, on, among, by, with",
    "original": "ἐν",
    "lang": "greek",
    "file": "G1722.html"
  },
  {
    "strongs": "G1785",
    "transliteration": "entolē",
    "gloss": "Commandment, order, instruction",
    "original": "ἐντολή",
    "lang": "greek",
    "file": "G1785.html"
  },
  {
    "strongs": "G18",
    "transliteration": "agathos",
    "gloss": "good, beneficial, upright",
    "original": "ἀγαθός",
    "lang": "greek",
    "file": "G18.html"
  },
  {
    "strongs": "G1849",
    "transliteration": "exousia",
    "gloss": "authority, power, right",
    "original": "ἐξουσία",
    "lang": "greek",
    "file": "G1849.html"
  },
  {
    "strongs": "G1860",
    "transliteration": "epangelia",
    "gloss": "promise, pledge, announcement",
    "original": "ἐπαγγελία",
    "lang": "greek",
    "file": "G1860.html"
  },
  {
    "strongs": "G189",
    "transliteration": "akoē",
    "gloss": "Hearing, report, rumor, ear",
    "original": "ἀκοή",
    "lang": "greek",
    "file": "G189.html"
  },
  {
    "strongs": "G190",
    "transliteration": "akoloutheō",
    "gloss": "to follow, to accompany, to be a disciple",
    "original": "ἀκολουθέω",
    "lang": "greek",
    "file": "G190.html"
  },
  {
    "strongs": "G1909",
    "transliteration": "epi",
    "gloss": "Upon, on, over, at, by, before",
    "original": "ἐπί",
    "lang": "greek",
    "file": "G1909.html"
  },
  {
    "strongs": "G191",
    "transliteration": "akouō",
    "gloss": "To hear, listen, understand",
    "original": "ἀκούω",
    "lang": "greek",
    "file": "G191.html"
  },
  {
    "strongs": "G1922",
    "transliteration": "epignōsis",
    "gloss": "knowledge, full knowledge, recognition",
    "original": "ἐπίγνωσις",
    "lang": "greek",
    "file": "G1922.html"
  },
  {
    "strongs": "G2036",
    "transliteration": "epō",
    "gloss": "to say, to speak, to tell",
    "original": "ἔπω",
    "lang": "greek",
    "file": "G2036.html"
  },
  {
    "strongs": "G2041",
    "transliteration": "ergon",
    "gloss": "Work, deed, action, task",
    "original": "ἔργον",
    "lang": "greek",
    "file": "G2041.html"
  },
  {
    "strongs": "G2064",
    "transliteration": "erchomai",
    "gloss": "to come, to go, to appear",
    "original": "ἔρχομαι",
    "lang": "greek",
    "file": "G2064.html"
  },
  {
    "strongs": "G2065",
    "transliteration": "Erotao",
    "gloss": "To ask, question, request",
    "original": "ἐρωτάω",
    "lang": "greek",
    "file": "G2065.html"
  },
  {
    "strongs": "G2098",
    "transliteration": "euangelion",
    "gloss": "gospel, good news, glad tidings",
    "original": "εὐαγγέλιον",
    "lang": "greek",
    "file": "G2098.html"
  },
  {
    "strongs": "G2127",
    "transliteration": "eulogeō",
    "gloss": "To bless, speak well of, praise",
    "original": "εὐλογέω",
    "lang": "greek",
    "file": "G2127.html"
  },
  {
    "strongs": "G2169",
    "transliteration": "eucharistia",
    "gloss": "thanksgiving, gratitude, the Eucharist",
    "original": "εὐχαριστία",
    "lang": "greek",
    "file": "G2169.html"
  },
  {
    "strongs": "G2198",
    "transliteration": "zaō",
    "gloss": "to live, to be alive, to have life",
    "original": "ζάω",
    "lang": "greek",
    "file": "G2198.html"
  },
  {
    "strongs": "G2222",
    "transliteration": "zōē",
    "gloss": "life, eternal life, vitality",
    "original": "ζωή",
    "lang": "greek",
    "file": "G2222.html"
  },
  {
    "strongs": "G225",
    "transliteration": "alētheia",
    "gloss": "truth, reality",
    "original": "ἀλήθεια",
    "lang": "greek",
    "file": "G225.html"
  },
  {
    "strongs": "G2250",
    "transliteration": "hēmera",
    "gloss": "Day, time, period",
    "original": "ἡμέρα",
    "lang": "greek",
    "file": "G2250.html"
  },
  {
    "strongs": "G227",
    "transliteration": "alēthēs",
    "gloss": "true, truthful, genuine",
    "original": "ἀληθής",
    "lang": "greek",
    "file": "G227.html"
  },
  {
    "strongs": "G2288",
    "transliteration": "thanatos",
    "gloss": "death, physical or spiritual death",
    "original": "θάνατος",
    "lang": "greek",
    "file": "G2288.html"
  },
  {
    "strongs": "G2293",
    "transliteration": "tharseō",
    "gloss": "To be of good courage, take heart",
    "original": "θαρσέω",
    "lang": "greek",
    "file": "G2293.html"
  },
  {
    "strongs": "G2307",
    "transliteration": "thelēma",
    "gloss": "will, desire, purpose",
    "original": "θέλημα",
    "lang": "greek",
    "file": "G2307.html"
  },
  {
    "strongs": "G2316",
    "transliteration": "theos",
    "gloss": "God, deity",
    "original": "θεός",
    "lang": "greek",
    "file": "G2316.html"
  },
  {
    "strongs": "G2347",
    "transliteration": "thlipsis",
    "gloss": "tribulation, affliction, distress",
    "original": "θλῖψις",
    "lang": "greek",
    "file": "G2347.html"
  },
  {
    "strongs": "G235",
    "transliteration": "alla",
    "gloss": "but, rather, on the contrary",
    "original": "ἀλλά",
    "lang": "greek",
    "file": "G235.html"
  },
  {
    "strongs": "G2372",
    "transliteration": "thymos",
    "gloss": "wrath, fury, passion",
    "original": "θυμός",
    "lang": "greek",
    "file": "G2372.html"
  },
  {
    "strongs": "G2378",
    "transliteration": "thysia",
    "gloss": "sacrifice, offering",
    "original": "θυσία",
    "lang": "greek",
    "file": "G2378.html"
  },
  {
    "strongs": "G240",
    "transliteration": "allēlōn",
    "gloss": "one another, each other, mutually",
    "original": "ἀλλήλων",
    "lang": "greek",
    "file": "G240.html"
  },
  {
    "strongs": "G2424",
    "transliteration": "Iēsous",
    "gloss": "Jesus, Joshua — 'YHWH saves'",
    "original": "Ἰησοῦς",
    "lang": "greek",
    "file": "G2424.html"
  },
  {
    "strongs": "G243",
    "transliteration": "allos",
    "gloss": "Another, other (of the same kind)",
    "original": "ἄλλος",
    "lang": "greek",
    "file": "G243.html"
  },
  {
    "strongs": "G2431",
    "transliteration": "hilaros",
    "gloss": "Cheerful, glad, joyous",
    "original": "ἱλαρός",
    "lang": "greek",
    "file": "G2431.html"
  },
  {
    "strongs": "G2434",
    "transliteration": "hilasmos",
    "gloss": "propitiation, atoning sacrifice, expiation",
    "original": "ἱλασμός",
    "lang": "greek",
    "file": "G2434.html"
  },
  {
    "strongs": "G2476",
    "transliteration": "histēmi",
    "gloss": "to stand, to set, to establish",
    "original": "ἵστημι",
    "lang": "greek",
    "file": "G2476.html"
  },
  {
    "strongs": "G25",
    "transliteration": "agapaō",
    "gloss": "to love, to cherish, to value",
    "original": "ἀγαπάω",
    "lang": "greek",
    "file": "G25.html"
  },
  {
    "strongs": "G2540",
    "transliteration": "kairos",
    "gloss": "time, season, appointed moment",
    "original": "καιρός",
    "lang": "greek",
    "file": "G2540.html"
  },
  {
    "strongs": "G2564",
    "transliteration": "kaleō",
    "gloss": "to call, to invite, to name",
    "original": "καλέω",
    "lang": "greek",
    "file": "G2564.html"
  },
  {
    "strongs": "G2588",
    "transliteration": "kardia",
    "gloss": "Heart, inner self, mind, will",
    "original": "καρδία",
    "lang": "greek",
    "file": "G2588.html"
  },
  {
    "strongs": "G26",
    "transliteration": "agapē",
    "gloss": "love, selfless love, charity",
    "original": "ἀγάπη",
    "lang": "greek",
    "file": "G26.html"
  },
  {
    "strongs": "G266",
    "transliteration": "hamartia",
    "gloss": "sin, missing the mark",
    "original": "ἁμαρτία",
    "lang": "greek",
    "file": "G266.html"
  },
  {
    "strongs": "G281",
    "transliteration": "amēn",
    "gloss": "amen, truly, so be it",
    "original": "ἀμήν",
    "lang": "greek",
    "file": "G281.html"
  },
  {
    "strongs": "G2842",
    "transliteration": "koinōnia",
    "gloss": "fellowship, communion, sharing",
    "original": "κοινωνία",
    "lang": "greek",
    "file": "G2842.html"
  },
  {
    "strongs": "G2889",
    "transliteration": "kosmos",
    "gloss": "world, universe, order",
    "original": "κόσμος",
    "lang": "greek",
    "file": "G2889.html"
  },
  {
    "strongs": "G2919",
    "transliteration": "krinō",
    "gloss": "to judge, to decide, to condemn",
    "original": "κρίνω",
    "lang": "greek",
    "file": "G2919.html"
  },
  {
    "strongs": "G2937",
    "transliteration": "ktisis",
    "gloss": "creation, creature, institution",
    "original": "κτίσις",
    "lang": "greek",
    "file": "G2937.html"
  },
  {
    "strongs": "G2962",
    "transliteration": "kyrios",
    "gloss": "Lord, master, sir",
    "original": "κύριος",
    "lang": "greek",
    "file": "G2962.html"
  },
  {
    "strongs": "G3004",
    "transliteration": "legō",
    "gloss": "to say, to speak, to tell",
    "original": "λέγω",
    "lang": "greek",
    "file": "G3004.html"
  },
  {
    "strongs": "G305",
    "transliteration": "anabainō",
    "gloss": "To go up, ascend, climb",
    "original": "ἀναβαίνω",
    "lang": "greek",
    "file": "G305.html"
  },
  {
    "strongs": "G3056",
    "transliteration": "logos",
    "gloss": "Word, message, reason, the Word",
    "original": "λόγος",
    "lang": "greek",
    "file": "G3056.html"
  },
  {
    "strongs": "G3076",
    "transliteration": "lypē",
    "gloss": "grief, sorrow, pain",
    "original": "λύπη",
    "lang": "greek",
    "file": "G3076.html"
  },
  {
    "strongs": "G3107",
    "transliteration": "makarios",
    "gloss": "blessed, happy, fortunate",
    "original": "μακάριος",
    "lang": "greek",
    "file": "G3107.html"
  },
  {
    "strongs": "G3115",
    "transliteration": "makrothymia",
    "gloss": "patience, longsuffering, endurance",
    "original": "μακροθυμία",
    "lang": "greek",
    "file": "G3115.html"
  },
  {
    "strongs": "G3140",
    "transliteration": "martyreō",
    "gloss": "to testify, to bear witness, to affirm",
    "original": "μαρτυρέω",
    "lang": "greek",
    "file": "G3140.html"
  },
  {
    "strongs": "G32",
    "transliteration": "angelos",
    "gloss": "angel, messenger",
    "original": "ἄγγελος",
    "lang": "greek",
    "file": "G32.html"
  },
  {
    "strongs": "G3306",
    "transliteration": "menō",
    "gloss": "To remain, abide, dwell, stay",
    "original": "μένω",
    "lang": "greek",
    "file": "G3306.html"
  },
  {
    "strongs": "G3340",
    "transliteration": "metanoeō",
    "gloss": "to repent, to change one's mind",
    "original": "μετανοέω",
    "lang": "greek",
    "file": "G3340.html"
  },
  {
    "strongs": "G3341",
    "transliteration": "metanoia",
    "gloss": "repentance, change of mind",
    "original": "μετάνοια",
    "lang": "greek",
    "file": "G3341.html"
  },
  {
    "strongs": "G3466",
    "transliteration": "mystērion",
    "gloss": "mystery, secret, hidden purpose",
    "original": "μυστήριον",
    "lang": "greek",
    "file": "G3466.html"
  },
  {
    "strongs": "G3474",
    "transliteration": "mōros",
    "gloss": "Foolish, stupid, dull",
    "original": "μωρός",
    "lang": "greek",
    "file": "G3474.html"
  },
  {
    "strongs": "G3485",
    "transliteration": "naos",
    "gloss": "temple, sanctuary, inner shrine",
    "original": "ναός",
    "lang": "greek",
    "file": "G3485.html"
  },
  {
    "strongs": "G3529",
    "transliteration": "nikē",
    "gloss": "victory, conquest, triumph",
    "original": "νίκη",
    "lang": "greek",
    "file": "G3529.html"
  },
  {
    "strongs": "G3551",
    "transliteration": "nomos",
    "gloss": "law, rule, principle",
    "original": "νόμος",
    "lang": "greek",
    "file": "G3551.html"
  },
  {
    "strongs": "G3563",
    "transliteration": "nous",
    "gloss": "Mind, understanding, intellect",
    "original": "νοῦς",
    "lang": "greek",
    "file": "G3563.html"
  },
  {
    "strongs": "G3568",
    "transliteration": "nyn",
    "gloss": "Now, at present, at this time",
    "original": "νῦν",
    "lang": "greek",
    "file": "G3568.html"
  },
  {
    "strongs": "G3598",
    "transliteration": "hodos",
    "gloss": "way, road, path, journey",
    "original": "ὁδός",
    "lang": "greek",
    "file": "G3598.html"
  },
  {
    "strongs": "G3622",
    "transliteration": "oikonomia",
    "gloss": "stewardship, administration, dispensation",
    "original": "οἰκονομία",
    "lang": "greek",
    "file": "G3622.html"
  },
  {
    "strongs": "G3624",
    "transliteration": "oikos",
    "gloss": "house, household, family, temple",
    "original": "οἶκος",
    "lang": "greek",
    "file": "G3624.html"
  },
  {
    "strongs": "G3629",
    "transliteration": "oiktirmōn",
    "gloss": "Compassionate, merciful, pitiful",
    "original": "οἰκτίρμων",
    "lang": "greek",
    "file": "G3629.html"
  },
  {
    "strongs": "G3670",
    "transliteration": "homologeō",
    "gloss": "to confess, to profess, to acknowledge",
    "original": "ὁμολογέω",
    "lang": "greek",
    "file": "G3670.html"
  },
  {
    "strongs": "G3709",
    "transliteration": "orgē",
    "gloss": "wrath, anger, indignation",
    "original": "ὀργή",
    "lang": "greek",
    "file": "G3709.html"
  },
  {
    "strongs": "G3772",
    "transliteration": "ouranos",
    "gloss": "heaven, sky, the heavens",
    "original": "οὐρανός",
    "lang": "greek",
    "file": "G3772.html"
  },
  {
    "strongs": "G3809",
    "transliteration": "paideia",
    "gloss": "Training, discipline, instruction, correction",
    "original": "παιδεία",
    "lang": "greek",
    "file": "G3809.html"
  },
  {
    "strongs": "G386",
    "transliteration": "anastasis",
    "gloss": "resurrection, rising up",
    "original": "ἀνάστασις",
    "lang": "greek",
    "file": "G386.html"
  },
  {
    "strongs": "G3870",
    "transliteration": "parakaleō",
    "gloss": "To call alongside, encourage, comfort, exhort",
    "original": "παρακαλέω",
    "lang": "greek",
    "file": "G3870.html"
  },
  {
    "strongs": "G3875",
    "transliteration": "paraklētos",
    "gloss": "Advocate, comforter, helper, intercessor",
    "original": "παράκλητος",
    "lang": "greek",
    "file": "G3875.html"
  },
  {
    "strongs": "G3952",
    "transliteration": "parousia",
    "gloss": "coming, arrival, presence",
    "original": "παρουσία",
    "lang": "greek",
    "file": "G3952.html"
  },
  {
    "strongs": "G3954",
    "transliteration": "parrēsia",
    "gloss": "boldness, confidence, openness",
    "original": "παρρησία",
    "lang": "greek",
    "file": "G3954.html"
  },
  {
    "strongs": "G3956",
    "transliteration": "pas",
    "gloss": "all, every, whole, each",
    "original": "πᾶς",
    "lang": "greek",
    "file": "G3956.html"
  },
  {
    "strongs": "G3982",
    "transliteration": "peithō",
    "gloss": "To persuade, trust, obey, have confidence",
    "original": "πείθω",
    "lang": "greek",
    "file": "G3982.html"
  },
  {
    "strongs": "G40",
    "transliteration": "hagios",
    "gloss": "holy, sacred, set apart",
    "original": "ἅγιος",
    "lang": "greek",
    "file": "G40.html"
  },
  {
    "strongs": "G4043",
    "transliteration": "peripateō",
    "gloss": "to walk, to live, to conduct oneself",
    "original": "περιπατέω",
    "lang": "greek",
    "file": "G4043.html"
  },
  {
    "strongs": "G4100",
    "transliteration": "pisteuō",
    "gloss": "to believe, to trust, to have faith",
    "original": "πιστεύω",
    "lang": "greek",
    "file": "G4100.html"
  },
  {
    "strongs": "G4102",
    "transliteration": "pistis",
    "gloss": "Faith, belief, trust, faithfulness",
    "original": "πίστις",
    "lang": "greek",
    "file": "G4102.html"
  },
  {
    "strongs": "G4137",
    "transliteration": "plēroō",
    "gloss": "to fulfill, to fill, to complete",
    "original": "πληρόω",
    "lang": "greek",
    "file": "G4137.html"
  },
  {
    "strongs": "G4151",
    "transliteration": "pneuma",
    "gloss": "spirit, breath, wind",
    "original": "πνεῦμα",
    "lang": "greek",
    "file": "G4151.html"
  },
  {
    "strongs": "G4152",
    "transliteration": "pneumatikos",
    "gloss": "spiritual, pertaining to the Spirit",
    "original": "πνευματικός",
    "lang": "greek",
    "file": "G4152.html"
  },
  {
    "strongs": "G4160",
    "transliteration": "poieō",
    "gloss": "to do, to make, to create",
    "original": "ποιέω",
    "lang": "greek",
    "file": "G4160.html"
  },
  {
    "strongs": "G4240",
    "transliteration": "prautēs",
    "gloss": "gentleness, meekness, humility",
    "original": "πραΰτης",
    "lang": "greek",
    "file": "G4240.html"
  },
  {
    "strongs": "G4335",
    "transliteration": "proseuchē",
    "gloss": "prayer, supplication",
    "original": "προσευχή",
    "lang": "greek",
    "file": "G4335.html"
  },
  {
    "strongs": "G435",
    "transliteration": "anēr",
    "gloss": "Man, husband, male person",
    "original": "ἀνήρ",
    "lang": "greek",
    "file": "G435.html"
  },
  {
    "strongs": "G4352",
    "transliteration": "proskyneō",
    "gloss": "to worship, to bow down, to pay homage",
    "original": "προσκυνέω",
    "lang": "greek",
    "file": "G4352.html"
  },
  {
    "strongs": "G4396",
    "transliteration": "prophētēs",
    "gloss": "prophet, spokesperson, foreteller",
    "original": "προφήτης",
    "lang": "greek",
    "file": "G4396.html"
  },
  {
    "strongs": "G444",
    "transliteration": "anthrōpos",
    "gloss": "human being, person, man",
    "original": "ἄνθρωπος",
    "lang": "greek",
    "file": "G444.html"
  },
  {
    "strongs": "G4487",
    "transliteration": "rhēma",
    "gloss": "Word, saying, utterance, matter",
    "original": "ῥῆμα",
    "lang": "greek",
    "file": "G4487.html"
  },
  {
    "strongs": "G450",
    "transliteration": "anistēmi",
    "gloss": "to raise up, to rise, to stand up",
    "original": "ἀνίστημι",
    "lang": "greek",
    "file": "G450.html"
  },
  {
    "strongs": "G4561",
    "transliteration": "sarx",
    "gloss": "flesh, human nature, sinful nature",
    "original": "σάρξ",
    "lang": "greek",
    "file": "G4561.html"
  },
  {
    "strongs": "G4592",
    "transliteration": "sēmeion",
    "gloss": "sign, miracle, wonder",
    "original": "σημεῖον",
    "lang": "greek",
    "file": "G4592.html"
  },
  {
    "strongs": "G4678",
    "transliteration": "sophia",
    "gloss": "wisdom, insight",
    "original": "σοφία",
    "lang": "greek",
    "file": "G4678.html"
  },
  {
    "strongs": "G4680",
    "transliteration": "sophos",
    "gloss": "wise, skilled, learned",
    "original": "σοφός",
    "lang": "greek",
    "file": "G4680.html"
  },
  {
    "strongs": "G4716",
    "transliteration": "stauros",
    "gloss": "cross, crucifixion stake",
    "original": "σταυρός",
    "lang": "greek",
    "file": "G4716.html"
  },
  {
    "strongs": "G4862",
    "transliteration": "syn",
    "gloss": "With, together with, accompanied by",
    "original": "σύν",
    "lang": "greek",
    "file": "G4862.html"
  },
  {
    "strongs": "G4982",
    "transliteration": "sōzō",
    "gloss": "to save, to deliver, to heal",
    "original": "σῴζω",
    "lang": "greek",
    "file": "G4982.html"
  },
  {
    "strongs": "G4991",
    "transliteration": "sōtēria",
    "gloss": "salvation, deliverance, preservation",
    "original": "σωτηρία",
    "lang": "greek",
    "file": "G4991.html"
  },
  {
    "strongs": "G5012",
    "transliteration": "tapeinophrosynē",
    "gloss": "humility, lowliness of mind",
    "original": "ταπεινοφροσύνη",
    "lang": "greek",
    "file": "G5012.html"
  },
  {
    "strongs": "G5046",
    "transliteration": "teleios",
    "gloss": "perfect, complete, mature",
    "original": "τέλειος",
    "lang": "greek",
    "file": "G5046.html"
  },
  {
    "strongs": "G5056",
    "transliteration": "telos",
    "gloss": "End, goal, purpose, completion",
    "original": "τέλος",
    "lang": "greek",
    "file": "G5056.html"
  },
  {
    "strongs": "G5083",
    "transliteration": "tēreō",
    "gloss": "to keep, to guard, to observe",
    "original": "τηρέω",
    "lang": "greek",
    "file": "G5083.html"
  },
  {
    "strongs": "G509",
    "transliteration": "anōthen",
    "gloss": "from above, again, anew",
    "original": "ἄνωθεν",
    "lang": "greek",
    "file": "G509.html"
  },
  {
    "strongs": "G515",
    "transliteration": "Axioo",
    "gloss": "To consider worthy, deem fit",
    "original": "ἀξιόω",
    "lang": "greek",
    "file": "G515.html"
  },
  {
    "strongs": "G5207",
    "transliteration": "huios",
    "gloss": "son, descendant, heir",
    "original": "υἱός",
    "lang": "greek",
    "file": "G5207.html"
  },
  {
    "strongs": "G5218",
    "transliteration": "hypakoē",
    "gloss": "Obedience, compliance, submission",
    "original": "ὑπακοή",
    "lang": "greek",
    "file": "G5218.html"
  },
  {
    "strongs": "G5219",
    "transliteration": "hypakouō",
    "gloss": "to obey, to listen, to submit",
    "original": "ὑπακούω",
    "lang": "greek",
    "file": "G5219.html"
  },
  {
    "strongs": "G5228",
    "transliteration": "hyper",
    "gloss": "for, on behalf of, above, beyond",
    "original": "ὑπέρ",
    "lang": "greek",
    "file": "G5228.html"
  },
  {
    "strongs": "G5281",
    "transliteration": "hypomonē",
    "gloss": "endurance, patience, perseverance",
    "original": "ὑπομονή",
    "lang": "greek",
    "file": "G5281.html"
  },
  {
    "strongs": "G5293",
    "transliteration": "hypotassō",
    "gloss": "To submit, subject, put in order under",
    "original": "ὑποτάσσω",
    "lang": "greek",
    "file": "G5293.html"
  },
  {
    "strongs": "G536",
    "transliteration": "aparchē",
    "gloss": "firstfruits, first portion",
    "original": "ἀπαρχή",
    "lang": "greek",
    "file": "G536.html"
  },
  {
    "strongs": "G5368",
    "transliteration": "phileō",
    "gloss": "to love, to have affection for, to kiss",
    "original": "φιλέω",
    "lang": "greek",
    "file": "G5368.html"
  },
  {
    "strongs": "G5457",
    "transliteration": "phōs",
    "gloss": "light, radiance, illumination",
    "original": "φῶς",
    "lang": "greek",
    "file": "G5457.html"
  },
  {
    "strongs": "G5479",
    "transliteration": "chara",
    "gloss": "Joy, gladness, delight",
    "original": "χαρά",
    "lang": "greek",
    "file": "G5479.html"
  },
  {
    "strongs": "G5483",
    "transliteration": "charizomai",
    "gloss": "to give freely, to forgive, to grant",
    "original": "χαρίζομαι",
    "lang": "greek",
    "file": "G5483.html"
  },
  {
    "strongs": "G5485",
    "transliteration": "charis",
    "gloss": "grace, favor, kindness",
    "original": "χάρις",
    "lang": "greek",
    "file": "G5485.html"
  },
  {
    "strongs": "G5547",
    "transliteration": "Christos",
    "gloss": "Christ, Messiah, Anointed One",
    "original": "Χριστός",
    "lang": "greek",
    "file": "G5547.html"
  },
  {
    "strongs": "G5590",
    "transliteration": "psychē",
    "gloss": "soul, life, self",
    "original": "ψυχή",
    "lang": "greek",
    "file": "G5590.html"
  },
  {
    "strongs": "G575",
    "transliteration": "apo",
    "gloss": "from, away from, since",
    "original": "ἀπό",
    "lang": "greek",
    "file": "G575.html"
  },
  {
    "strongs": "G602",
    "transliteration": "apokalypsis",
    "gloss": "revelation, unveiling, disclosure",
    "original": "ἀποκάλυψις",
    "lang": "greek",
    "file": "G602.html"
  },
  {
    "strongs": "G622",
    "transliteration": "apollymi",
    "gloss": "to destroy, to lose, to perish",
    "original": "ἀπόλλυμι",
    "lang": "greek",
    "file": "G622.html"
  },
  {
    "strongs": "G629",
    "transliteration": "apolytrōsis",
    "gloss": "redemption, release, deliverance",
    "original": "ἀπολύτρωσις",
    "lang": "greek",
    "file": "G629.html"
  },
  {
    "strongs": "G649",
    "transliteration": "apostellō",
    "gloss": "To send forth, send out, commission",
    "original": "ἀποστέλλω",
    "lang": "greek",
    "file": "G649.html"
  },
  {
    "strongs": "G652",
    "transliteration": "apostolos",
    "gloss": "apostle, sent one, messenger",
    "original": "ἀπόστολος",
    "lang": "greek",
    "file": "G652.html"
  },
  {
    "strongs": "G684",
    "transliteration": "apōleia",
    "gloss": "Destruction, perdition, waste",
    "original": "ἀπώλεια",
    "lang": "greek",
    "file": "G684.html"
  },
  {
    "strongs": "G71",
    "transliteration": "agō",
    "gloss": "To lead, bring, carry, guide",
    "original": "ἄγω",
    "lang": "greek",
    "file": "G71.html"
  },
  {
    "strongs": "G746",
    "transliteration": "archē",
    "gloss": "beginning, origin, ruler, authority",
    "original": "ἀρχή",
    "lang": "greek",
    "file": "G746.html"
  },
  {
    "strongs": "G769",
    "transliteration": "astheneia",
    "gloss": "weakness, sickness, infirmity",
    "original": "ἀσθένεια",
    "lang": "greek",
    "file": "G769.html"
  },
  {
    "strongs": "G80",
    "transliteration": "adelphos",
    "gloss": "brother, fellow believer",
    "original": "ἀδελφός",
    "lang": "greek",
    "file": "G80.html"
  },
  {
    "strongs": "G846",
    "transliteration": "autos",
    "gloss": "he, she, it, self, same",
    "original": "αὐτός",
    "lang": "greek",
    "file": "G846.html"
  },
  {
    "strongs": "G906",
    "transliteration": "ballō",
    "gloss": "To throw, cast, put, place",
    "original": "βάλλω",
    "lang": "greek",
    "file": "G906.html"
  },
  {
    "strongs": "G907",
    "transliteration": "baptizō",
    "gloss": "to baptize, to immerse, to wash",
    "original": "βαπτίζω",
    "lang": "greek",
    "file": "G907.html"
  },
  {
    "strongs": "G932",
    "transliteration": "basileia",
    "gloss": "kingdom, reign, royal power",
    "original": "βασιλεία",
    "lang": "greek",
    "file": "G932.html"
  },
  {
    "strongs": "G935",
    "transliteration": "basileus",
    "gloss": "king, sovereign, ruler",
    "original": "βασιλεύς",
    "lang": "greek",
    "file": "G935.html"
  },
  {
    "strongs": "H1",
    "transliteration": "Ab",
    "gloss": "Father",
    "original": "אָב",
    "lang": "hebrew",
    "file": "H1.html"
  },
  {
    "strongs": "H1004",
    "transliteration": "Bayith",
    "gloss": "House, household, temple",
    "original": "בַּיִת",
    "lang": "hebrew",
    "file": "H1004.html"
  },
  {
    "strongs": "H1058",
    "transliteration": "bākâ",
    "gloss": "To weep, cry, shed tears",
    "original": "בָּכָה",
    "lang": "hebrew",
    "file": "H1058.html"
  },
  {
    "strongs": "H1121",
    "transliteration": "Ben",
    "gloss": "Son, child, descendant",
    "original": "בֵּן",
    "lang": "hebrew",
    "file": "H1121.html"
  },
  {
    "strongs": "H1129",
    "transliteration": "bānâ",
    "gloss": "To build, construct, establish",
    "original": "בָּנָה",
    "lang": "hebrew",
    "file": "H1129.html"
  },
  {
    "strongs": "H113",
    "transliteration": "ʾādôn",
    "gloss": "Lord, master, sovereign",
    "original": "אָדוֹן",
    "lang": "hebrew",
    "file": "H113.html"
  },
  {
    "strongs": "H120",
    "transliteration": "Adam",
    "gloss": "Man, mankind, Adam",
    "original": "אָדָם",
    "lang": "hebrew",
    "file": "H120.html"
  },
  {
    "strongs": "H1242",
    "transliteration": "Boqer",
    "gloss": "Morning, dawn",
    "original": "בֹּקֶר",
    "lang": "hebrew",
    "file": "H1242.html"
  },
  {
    "strongs": "H1245",
    "transliteration": "bāqash",
    "gloss": "To seek, search for, request",
    "original": "בָּקַשׁ",
    "lang": "hebrew",
    "file": "H1245.html"
  },
  {
    "strongs": "H1254",
    "transliteration": "Bara",
    "gloss": "To create",
    "original": "בָּרָא",
    "lang": "hebrew",
    "file": "H1254.html"
  },
  {
    "strongs": "H127",
    "transliteration": "adamah",
    "gloss": "ground, earth, soil",
    "original": "אֲדָמָה",
    "lang": "hebrew",
    "file": "H127.html"
  },
  {
    "strongs": "H1285",
    "transliteration": "berith",
    "gloss": "covenant, alliance, pledge",
    "original": "בְּרִית",
    "lang": "hebrew",
    "file": "H1285.html"
  },
  {
    "strongs": "H1288",
    "transliteration": "barak",
    "gloss": "to bless, to praise",
    "original": "בָּרַךְ",
    "lang": "hebrew",
    "file": "H1288.html"
  },
  {
    "strongs": "H1293",
    "transliteration": "berakah",
    "gloss": "blessing",
    "original": "בְּרָכָה",
    "lang": "hebrew",
    "file": "H1293.html"
  },
  {
    "strongs": "H1323",
    "transliteration": "bath",
    "gloss": "daughter",
    "original": "בַּת",
    "lang": "hebrew",
    "file": "H1323.html"
  },
  {
    "strongs": "H1350",
    "transliteration": "Gaal",
    "gloss": "To redeem, act as kinsman-redeemer",
    "original": "גָּאַל",
    "lang": "hebrew",
    "file": "H1350.html"
  },
  {
    "strongs": "H1366",
    "transliteration": "Gebul",
    "gloss": "Border, boundary, territory",
    "original": "גְּבוּל",
    "lang": "hebrew",
    "file": "H1366.html"
  },
  {
    "strongs": "H1368",
    "transliteration": "gibbor",
    "gloss": "mighty, warrior",
    "original": "גִּבּוֹר",
    "lang": "hebrew",
    "file": "H1368.html"
  },
  {
    "strongs": "H1397",
    "transliteration": "geber",
    "gloss": "man, warrior",
    "original": "גֶּבֶר",
    "lang": "hebrew",
    "file": "H1397.html"
  },
  {
    "strongs": "H1419",
    "transliteration": "Gadol",
    "gloss": "Great, large, mighty",
    "original": "גָּדוֹל",
    "lang": "hebrew",
    "file": "H1419.html"
  },
  {
    "strongs": "H1431",
    "transliteration": "gādal",
    "gloss": "To be great, grow up, magnify",
    "original": "גָּדַל",
    "lang": "hebrew",
    "file": "H1431.html"
  },
  {
    "strongs": "H1471",
    "transliteration": "Goy",
    "gloss": "Nation, people, Gentiles",
    "original": "גּוֹי",
    "lang": "hebrew",
    "file": "H1471.html"
  },
  {
    "strongs": "H157",
    "transliteration": "ahab",
    "gloss": "to love, desire, delight in",
    "original": "אָהַב",
    "lang": "hebrew",
    "file": "H157.html"
  },
  {
    "strongs": "H1588",
    "transliteration": "gan",
    "gloss": "Garden, enclosed garden",
    "original": "גַּן",
    "lang": "hebrew",
    "file": "H1588.html"
  },
  {
    "strongs": "H1616",
    "transliteration": "gēr",
    "gloss": "Sojourner, resident alien, stranger",
    "original": "גֵּר",
    "lang": "hebrew",
    "file": "H1616.html"
  },
  {
    "strongs": "H1696",
    "transliteration": "Dabar",
    "gloss": "To speak, declare, command",
    "original": "דָּבַר",
    "lang": "hebrew",
    "file": "H1696.html"
  },
  {
    "strongs": "H1697",
    "transliteration": "dabar",
    "gloss": "word, matter, thing",
    "original": "דָּבָר",
    "lang": "hebrew",
    "file": "H1697.html"
  },
  {
    "strongs": "H1755",
    "transliteration": "dôr",
    "gloss": "Generation, age, period",
    "original": "דּוֹר",
    "lang": "hebrew",
    "file": "H1755.html"
  },
  {
    "strongs": "H1818",
    "transliteration": "dām",
    "gloss": "Blood",
    "original": "דָּם",
    "lang": "hebrew",
    "file": "H1818.html"
  },
  {
    "strongs": "H1870",
    "transliteration": "Derek",
    "gloss": "Way, road, path, manner",
    "original": "דֶּרֶךְ",
    "lang": "hebrew",
    "file": "H1870.html"
  },
  {
    "strongs": "H1875",
    "transliteration": "dārash",
    "gloss": "To seek, inquire, study, require",
    "original": "דָּרַשׁ",
    "lang": "hebrew",
    "file": "H1875.html"
  },
  {
    "strongs": "H1961",
    "transliteration": "Hayah",
    "gloss": "To be, become, exist",
    "original": "הָיָה",
    "lang": "hebrew",
    "file": "H1961.html"
  },
  {
    "strongs": "H1980",
    "transliteration": "halak",
    "gloss": "to walk, to go",
    "original": "הָלַךְ",
    "lang": "hebrew",
    "file": "H1980.html"
  },
  {
    "strongs": "H1984",
    "transliteration": "halal",
    "gloss": "to praise, boast, shine",
    "original": "הָלַל",
    "lang": "hebrew",
    "file": "H1984.html"
  },
  {
    "strongs": "H2009",
    "transliteration": "Hinneh",
    "gloss": "Behold! Look! See!",
    "original": "הִנֵּה",
    "lang": "hebrew",
    "file": "H2009.html"
  },
  {
    "strongs": "H2015",
    "transliteration": "Haphak",
    "gloss": "To turn, overturn, transform",
    "original": "הָפַךְ",
    "lang": "hebrew",
    "file": "H2015.html"
  },
  {
    "strongs": "H2022",
    "transliteration": "har",
    "gloss": "Mountain, hill, hill country",
    "original": "הַר",
    "lang": "hebrew",
    "file": "H2022.html"
  },
  {
    "strongs": "H2063",
    "transliteration": "Zoth",
    "gloss": "This",
    "original": "זֹאת",
    "lang": "hebrew",
    "file": "H2063.html"
  },
  {
    "strongs": "H2077",
    "transliteration": "zebach",
    "gloss": "Sacrifice, offering",
    "original": "זֶבַח",
    "lang": "hebrew",
    "file": "H2077.html"
  },
  {
    "strongs": "H2088",
    "transliteration": "Zeh",
    "gloss": "This",
    "original": "זֶה",
    "lang": "hebrew",
    "file": "H2088.html"
  },
  {
    "strongs": "H2091",
    "transliteration": "Zahab",
    "gloss": "Gold",
    "original": "זָהָב",
    "lang": "hebrew",
    "file": "H2091.html"
  },
  {
    "strongs": "H2142",
    "transliteration": "Zakar",
    "gloss": "To remember, recall, mention",
    "original": "זָכַר",
    "lang": "hebrew",
    "file": "H2142.html"
  },
  {
    "strongs": "H2167",
    "transliteration": "Zamar",
    "gloss": "To sing praise, make music",
    "original": "זָמַר",
    "lang": "hebrew",
    "file": "H2167.html"
  },
  {
    "strongs": "H2233",
    "transliteration": "Zera",
    "gloss": "Seed, offspring, descendant",
    "original": "זֶרַע",
    "lang": "hebrew",
    "file": "H2233.html"
  },
  {
    "strongs": "H226",
    "transliteration": "ʾôt",
    "gloss": "Sign, mark, token",
    "original": "אוֹת",
    "lang": "hebrew",
    "file": "H226.html"
  },
  {
    "strongs": "H2319",
    "transliteration": "Chadash",
    "gloss": "New, fresh",
    "original": "חָדָשׁ",
    "lang": "hebrew",
    "file": "H2319.html"
  },
  {
    "strongs": "H2388",
    "transliteration": "chazaq",
    "gloss": "to be strong, strengthen",
    "original": "חָזַק",
    "lang": "hebrew",
    "file": "H2388.html"
  },
  {
    "strongs": "H2398",
    "transliteration": "Chata",
    "gloss": "To sin, miss the mark",
    "original": "חָטָא",
    "lang": "hebrew",
    "file": "H2398.html"
  },
  {
    "strongs": "H2403",
    "transliteration": "chattath",
    "gloss": "sin, sin offering",
    "original": "חַטָּאת",
    "lang": "hebrew",
    "file": "H2403.html"
  },
  {
    "strongs": "H2416",
    "transliteration": "Chay",
    "gloss": "Living, alive, life",
    "original": "חַי",
    "lang": "hebrew",
    "file": "H2416.html"
  },
  {
    "strongs": "H2421",
    "transliteration": "chāyâ",
    "gloss": "To live, be alive, revive",
    "original": "חָיָה",
    "lang": "hebrew",
    "file": "H2421.html"
  },
  {
    "strongs": "H2428",
    "transliteration": "Chayil",
    "gloss": "Strength, valor, wealth, army",
    "original": "חַיִל",
    "lang": "hebrew",
    "file": "H2428.html"
  },
  {
    "strongs": "H2451",
    "transliteration": "Chokmah",
    "gloss": "Wisdom, skill, insight",
    "original": "חׇכְמָה",
    "lang": "hebrew",
    "file": "H2451.html"
  },
  {
    "strongs": "H2490",
    "transliteration": "chalal",
    "gloss": "To profane, pierce, begin, pollute",
    "original": "חָלַל",
    "lang": "hebrew",
    "file": "H2490.html"
  },
  {
    "strongs": "H251",
    "transliteration": "Ach",
    "gloss": "Brother, kinsman",
    "original": "אָח",
    "lang": "hebrew",
    "file": "H251.html"
  },
  {
    "strongs": "H2534",
    "transliteration": "chēmâ",
    "gloss": "Wrath, fury, hot anger; venom",
    "original": "חֵמָה",
    "lang": "hebrew",
    "file": "H2534.html"
  },
  {
    "strongs": "H2580",
    "transliteration": "chen",
    "gloss": "grace, favor, charm",
    "original": "חֵן",
    "lang": "hebrew",
    "file": "H2580.html"
  },
  {
    "strongs": "H259",
    "transliteration": "Echad",
    "gloss": "One, united",
    "original": "אֶחָד",
    "lang": "hebrew",
    "file": "H259.html"
  },
  {
    "strongs": "H2603",
    "transliteration": "Chanan",
    "gloss": "To be gracious, show favor",
    "original": "חָנַן",
    "lang": "hebrew",
    "file": "H2603.html"
  },
  {
    "strongs": "H2617",
    "transliteration": "chesed",
    "gloss": "lovingkindness, mercy, steadfast love",
    "original": "חֶסֶד",
    "lang": "hebrew",
    "file": "H2617.html"
  },
  {
    "strongs": "H2623",
    "transliteration": "Chasid",
    "gloss": "Faithful, devout, godly",
    "original": "חָסִיד",
    "lang": "hebrew",
    "file": "H2623.html"
  },
  {
    "strongs": "H2654",
    "transliteration": "chāphēts",
    "gloss": "To delight in, take pleasure in, desire",
    "original": "חָפֵץ",
    "lang": "hebrew",
    "file": "H2654.html"
  },
  {
    "strongs": "H2706",
    "transliteration": "Choq",
    "gloss": "Statute, decree, ordinance",
    "original": "חֹק",
    "lang": "hebrew",
    "file": "H2706.html"
  },
  {
    "strongs": "H2713",
    "transliteration": "chāqar",
    "gloss": "To search out, explore, examine",
    "original": "חָקַר",
    "lang": "hebrew",
    "file": "H2713.html"
  },
  {
    "strongs": "H2803",
    "transliteration": "Chashab",
    "gloss": "To think, plan, reckon",
    "original": "חָשַׁב",
    "lang": "hebrew",
    "file": "H2803.html"
  },
  {
    "strongs": "H2820",
    "transliteration": "chasak",
    "gloss": "To withhold, restrain, spare",
    "original": "חָשַׂךְ",
    "lang": "hebrew",
    "file": "H2820.html"
  },
  {
    "strongs": "H2859",
    "transliteration": "chathan",
    "gloss": "To become a son-in-law, bridegroom",
    "original": "חָתַן",
    "lang": "hebrew",
    "file": "H2859.html"
  },
  {
    "strongs": "H2889",
    "transliteration": "Tahor",
    "gloss": "Clean, pure",
    "original": "טָהוֹר",
    "lang": "hebrew",
    "file": "H2889.html"
  },
  {
    "strongs": "H2896",
    "transliteration": "Tov",
    "gloss": "Good, pleasant, beautiful",
    "original": "טוֹב",
    "lang": "hebrew",
    "file": "H2896.html"
  },
  {
    "strongs": "H3027",
    "transliteration": "Yad",
    "gloss": "Hand, power, side",
    "original": "יָד",
    "lang": "hebrew",
    "file": "H3027.html"
  },
  {
    "strongs": "H3034",
    "transliteration": "Yadah",
    "gloss": "To give thanks, praise, confess",
    "original": "יָדָה",
    "lang": "hebrew",
    "file": "H3034.html"
  },
  {
    "strongs": "H3045",
    "transliteration": "yada",
    "gloss": "to know, perceive, discern",
    "original": "יָדַע",
    "lang": "hebrew",
    "file": "H3045.html"
  },
  {
    "strongs": "H3068",
    "transliteration": "YHWH (Yahweh)",
    "gloss": "LORD, the proper name of God",
    "original": "יְהוָה",
    "lang": "hebrew",
    "file": "H3068.html"
  },
  {
    "strongs": "H310",
    "transliteration": "ʾachar",
    "gloss": "After, behind, following",
    "original": "אַחַר",
    "lang": "hebrew",
    "file": "H310.html"
  },
  {
    "strongs": "H3190",
    "transliteration": "Yatav",
    "gloss": "To be good, do well, please",
    "original": "יָטַב",
    "lang": "hebrew",
    "file": "H3190.html"
  },
  {
    "strongs": "H3254",
    "transliteration": "Yasaph",
    "gloss": "To add, increase, do again",
    "original": "יָסַף",
    "lang": "hebrew",
    "file": "H3254.html"
  },
  {
    "strongs": "H3374",
    "transliteration": "Yirah",
    "gloss": "Fear, reverence, awe",
    "original": "יִרְאָה",
    "lang": "hebrew",
    "file": "H3374.html"
  },
  {
    "strongs": "H3381",
    "transliteration": "Yarad",
    "gloss": "To go down, descend",
    "original": "יָרַד",
    "lang": "hebrew",
    "file": "H3381.html"
  },
  {
    "strongs": "H3384",
    "transliteration": "yarah",
    "gloss": "To throw, shoot, instruct, teach",
    "original": "יָרָה",
    "lang": "hebrew",
    "file": "H3384.html"
  },
  {
    "strongs": "H341",
    "transliteration": "ʾôyēb",
    "gloss": "Enemy, foe, adversary",
    "original": "אֹיֵב",
    "lang": "hebrew",
    "file": "H341.html"
  },
  {
    "strongs": "H3427",
    "transliteration": "Yashab",
    "gloss": "To sit, dwell, remain",
    "original": "יָשַׁב",
    "lang": "hebrew",
    "file": "H3427.html"
  },
  {
    "strongs": "H3444",
    "transliteration": "yeshuah",
    "gloss": "salvation, deliverance",
    "original": "יְשׁוּעָה",
    "lang": "hebrew",
    "file": "H3444.html"
  },
  {
    "strongs": "H3467",
    "transliteration": "Yasha",
    "gloss": "To save, deliver, rescue",
    "original": "יָשַׁע",
    "lang": "hebrew",
    "file": "H3467.html"
  },
  {
    "strongs": "H3477",
    "transliteration": "Yashar",
    "gloss": "Straight, right, upright",
    "original": "יָשָׁר",
    "lang": "hebrew",
    "file": "H3477.html"
  },
  {
    "strongs": "H3513",
    "transliteration": "Kabad",
    "gloss": "To be heavy, honored, glorified",
    "original": "כָּבַד",
    "lang": "hebrew",
    "file": "H3513.html"
  },
  {
    "strongs": "H3519",
    "transliteration": "kabod",
    "gloss": "glory, honor, splendor",
    "original": "כָּבוֹד",
    "lang": "hebrew",
    "file": "H3519.html"
  },
  {
    "strongs": "H3559",
    "transliteration": "kun",
    "gloss": "To establish, prepare, be firm",
    "original": "כּוּן",
    "lang": "hebrew",
    "file": "H3559.html"
  },
  {
    "strongs": "H3581",
    "transliteration": "koach",
    "gloss": "strength, power, ability",
    "original": "כֹּחַ",
    "lang": "hebrew",
    "file": "H3581.html"
  },
  {
    "strongs": "H3605",
    "transliteration": "Kol",
    "gloss": "All, every, whole",
    "original": "כֹּל",
    "lang": "hebrew",
    "file": "H3605.html"
  },
  {
    "strongs": "H3615",
    "transliteration": "Kalah",
    "gloss": "To complete, finish, consume",
    "original": "כָּלָה",
    "lang": "hebrew",
    "file": "H3615.html"
  },
  {
    "strongs": "H3651",
    "transliteration": "Ken",
    "gloss": "So, thus, right, true",
    "original": "כֵּן",
    "lang": "hebrew",
    "file": "H3651.html"
  },
  {
    "strongs": "H376",
    "transliteration": "Ish",
    "gloss": "Man, husband, person",
    "original": "אִישׁ",
    "lang": "hebrew",
    "file": "H376.html"
  },
  {
    "strongs": "H3766",
    "transliteration": "Kara",
    "gloss": "To bow down, kneel",
    "original": "כָּרַע",
    "lang": "hebrew",
    "file": "H3766.html"
  },
  {
    "strongs": "H3808",
    "transliteration": "Lo",
    "gloss": "Not, no",
    "original": "לֹא",
    "lang": "hebrew",
    "file": "H3808.html"
  },
  {
    "strongs": "H3820",
    "transliteration": "leb",
    "gloss": "heart, mind, inner self",
    "original": "לֵב",
    "lang": "hebrew",
    "file": "H3820.html"
  },
  {
    "strongs": "H3824",
    "transliteration": "Lebab",
    "gloss": "Heart, mind, inner person",
    "original": "לֵבָב",
    "lang": "hebrew",
    "file": "H3824.html"
  },
  {
    "strongs": "H3947",
    "transliteration": "laqach",
    "gloss": "To take, receive, seize, bring",
    "original": "לָקַח",
    "lang": "hebrew",
    "file": "H3947.html"
  },
  {
    "strongs": "H3966",
    "transliteration": "Meod",
    "gloss": "Very, exceedingly, greatly",
    "original": "מְאֹד",
    "lang": "hebrew",
    "file": "H3966.html"
  },
  {
    "strongs": "H398",
    "transliteration": "ʾākal",
    "gloss": "To eat, consume, devour",
    "original": "אָכַל",
    "lang": "hebrew",
    "file": "H398.html"
  },
  {
    "strongs": "H4043",
    "transliteration": "magen",
    "gloss": "Shield, buckler, protector",
    "original": "מָגֵן",
    "lang": "hebrew",
    "file": "H4043.html"
  },
  {
    "strongs": "H410",
    "transliteration": "El",
    "gloss": "God, mighty one",
    "original": "אֵל",
    "lang": "hebrew",
    "file": "H410.html"
  },
  {
    "strongs": "H4100",
    "transliteration": "Mah",
    "gloss": "What? How? Why?",
    "original": "מָה",
    "lang": "hebrew",
    "file": "H4100.html"
  },
  {
    "strongs": "H4116",
    "transliteration": "mahar",
    "gloss": "To hasten, hurry, be quick",
    "original": "מָהַר",
    "lang": "hebrew",
    "file": "H4116.html"
  },
  {
    "strongs": "H4150",
    "transliteration": "moed",
    "gloss": "Appointed time, meeting place, feast",
    "original": "מוֹעֵד",
    "lang": "hebrew",
    "file": "H4150.html"
  },
  {
    "strongs": "H4191",
    "transliteration": "Muth",
    "gloss": "To die, put to death",
    "original": "מוּת",
    "lang": "hebrew",
    "file": "H4191.html"
  },
  {
    "strongs": "H4264",
    "transliteration": "Machaneh",
    "gloss": "Camp, encampment, army",
    "original": "מַחֲנֶה",
    "lang": "hebrew",
    "file": "H4264.html"
  },
  {
    "strongs": "H430",
    "transliteration": "Elohim",
    "gloss": "God, gods",
    "original": "אֱלֹהִים",
    "lang": "hebrew",
    "file": "H430.html"
  },
  {
    "strongs": "H4310",
    "transliteration": "Mi",
    "gloss": "Who?",
    "original": "מִי",
    "lang": "hebrew",
    "file": "H4310.html"
  },
  {
    "strongs": "H4397",
    "transliteration": "Malak",
    "gloss": "Messenger, angel",
    "original": "מַלְאָךְ",
    "lang": "hebrew",
    "file": "H4397.html"
  },
  {
    "strongs": "H4427",
    "transliteration": "Malak",
    "gloss": "To reign, be king, rule",
    "original": "מָלַךְ",
    "lang": "hebrew",
    "file": "H4427.html"
  },
  {
    "strongs": "H4428",
    "transliteration": "Melek",
    "gloss": "King, ruler",
    "original": "מֶלֶךְ",
    "lang": "hebrew",
    "file": "H4428.html"
  },
  {
    "strongs": "H4480",
    "transliteration": "Min",
    "gloss": "From, out of, because of",
    "original": "מִן",
    "lang": "hebrew",
    "file": "H4480.html"
  },
  {
    "strongs": "H4639",
    "transliteration": "ma'aseh",
    "gloss": "Work, deed, act, thing made",
    "original": "מַעֲשֶׂה",
    "lang": "hebrew",
    "file": "H4639.html"
  },
  {
    "strongs": "H4687",
    "transliteration": "Mitsvah",
    "gloss": "Commandment, command",
    "original": "מִצְוָה",
    "lang": "hebrew",
    "file": "H4687.html"
  },
  {
    "strongs": "H4725",
    "transliteration": "Maqom",
    "gloss": "Place, standing",
    "original": "מָקוֹם",
    "lang": "hebrew",
    "file": "H4725.html"
  },
  {
    "strongs": "H4872",
    "transliteration": "Mosheh",
    "gloss": "Moses",
    "original": "מֹשֶׁה",
    "lang": "hebrew",
    "file": "H4872.html"
  },
  {
    "strongs": "H4941",
    "transliteration": "mishpat",
    "gloss": "justice, judgment, ordinance",
    "original": "מִשְׁפָּט",
    "lang": "hebrew",
    "file": "H4941.html"
  },
  {
    "strongs": "H4994",
    "transliteration": "na",
    "gloss": "Please, now, I pray",
    "original": "נָא",
    "lang": "hebrew",
    "file": "H4994.html"
  },
  {
    "strongs": "H5002",
    "transliteration": "Neum",
    "gloss": "Utterance, declaration, oracle",
    "original": "נְאֻם",
    "lang": "hebrew",
    "file": "H5002.html"
  },
  {
    "strongs": "H5046",
    "transliteration": "Nagad",
    "gloss": "To declare, tell, make known",
    "original": "נָגַד",
    "lang": "hebrew",
    "file": "H5046.html"
  },
  {
    "strongs": "H5157",
    "transliteration": "Nachal",
    "gloss": "To inherit, take possession",
    "original": "נָחַל",
    "lang": "hebrew",
    "file": "H5157.html"
  },
  {
    "strongs": "H5162",
    "transliteration": "Nacham",
    "gloss": "To comfort, repent, relent",
    "original": "נָחַם",
    "lang": "hebrew",
    "file": "H5162.html"
  },
  {
    "strongs": "H517",
    "transliteration": "em",
    "gloss": "mother",
    "original": "אֵם",
    "lang": "hebrew",
    "file": "H517.html"
  },
  {
    "strongs": "H5186",
    "transliteration": "Natah",
    "gloss": "To stretch out, extend, turn",
    "original": "נָטָה",
    "lang": "hebrew",
    "file": "H5186.html"
  },
  {
    "strongs": "H5227",
    "transliteration": "nokach",
    "gloss": "In front of, opposite, straight ahead",
    "original": "נֹכַח",
    "lang": "hebrew",
    "file": "H5227.html"
  },
  {
    "strongs": "H530",
    "transliteration": "ʾĕmûnâ",
    "gloss": "Faithfulness, steadfastness, fidelity",
    "original": "אֱמוּנָה",
    "lang": "hebrew",
    "file": "H530.html"
  },
  {
    "strongs": "H5307",
    "transliteration": "Naphal",
    "gloss": "To fall, lie down, cast down",
    "original": "נָפַל",
    "lang": "hebrew",
    "file": "H5307.html"
  },
  {
    "strongs": "H5315",
    "transliteration": "nephesh",
    "gloss": "soul, life, being, breath",
    "original": "נֶפֶשׁ",
    "lang": "hebrew",
    "file": "H5315.html"
  },
  {
    "strongs": "H5324",
    "transliteration": "natsab",
    "gloss": "To stand, take one's stand, be stationed",
    "original": "נָצַב",
    "lang": "hebrew",
    "file": "H5324.html"
  },
  {
    "strongs": "H5329",
    "transliteration": "natsach",
    "gloss": "To oversee, direct, lead (music)",
    "original": "נָצַח",
    "lang": "hebrew",
    "file": "H5329.html"
  },
  {
    "strongs": "H5337",
    "transliteration": "natsal",
    "gloss": "To deliver, rescue, snatch away",
    "original": "נָצַל",
    "lang": "hebrew",
    "file": "H5337.html"
  },
  {
    "strongs": "H5375",
    "transliteration": "Nasa",
    "gloss": "To lift, carry, bear, forgive",
    "original": "נָשָׂא",
    "lang": "hebrew",
    "file": "H5375.html"
  },
  {
    "strongs": "H539",
    "transliteration": "aman",
    "gloss": "to believe, be faithful, be firm",
    "original": "אָמַן",
    "lang": "hebrew",
    "file": "H539.html"
  },
  {
    "strongs": "H5397",
    "transliteration": "neshamah",
    "gloss": "Breath, breath of life, spirit",
    "original": "נְשָׁמָה",
    "lang": "hebrew",
    "file": "H5397.html"
  },
  {
    "strongs": "H5414",
    "transliteration": "Nathan",
    "gloss": "To give, set, put, grant",
    "original": "נָתַן",
    "lang": "hebrew",
    "file": "H5414.html"
  },
  {
    "strongs": "H5493",
    "transliteration": "Sur",
    "gloss": "To turn aside, depart, remove",
    "original": "סוּר",
    "lang": "hebrew",
    "file": "H5493.html"
  },
  {
    "strongs": "H5541",
    "transliteration": "selah",
    "gloss": "Pause, lift up, exalt",
    "original": "סָלָה",
    "lang": "hebrew",
    "file": "H5541.html"
  },
  {
    "strongs": "H5545",
    "transliteration": "salach",
    "gloss": "to forgive, pardon",
    "original": "סָלַח",
    "lang": "hebrew",
    "file": "H5545.html"
  },
  {
    "strongs": "H559",
    "transliteration": "Amar",
    "gloss": "To say, speak, command",
    "original": "אָמַר",
    "lang": "hebrew",
    "file": "H559.html"
  },
  {
    "strongs": "H5612",
    "transliteration": "sepher",
    "gloss": "Book, scroll, document, letter",
    "original": "סֵפֶר",
    "lang": "hebrew",
    "file": "H5612.html"
  },
  {
    "strongs": "H5650",
    "transliteration": "Ebed",
    "gloss": "Servant, slave, worshiper",
    "original": "עֶבֶד",
    "lang": "hebrew",
    "file": "H5650.html"
  },
  {
    "strongs": "H571",
    "transliteration": "emeth",
    "gloss": "truth, faithfulness, reliability",
    "original": "אֱמֶת",
    "lang": "hebrew",
    "file": "H571.html"
  },
  {
    "strongs": "H5715",
    "transliteration": "Eduth",
    "gloss": "Testimony, witness",
    "original": "עֵדוּת",
    "lang": "hebrew",
    "file": "H5715.html"
  },
  {
    "strongs": "H5769",
    "transliteration": "Olam",
    "gloss": "Eternity, forever, ancient",
    "original": "עוֹלָם",
    "lang": "hebrew",
    "file": "H5769.html"
  },
  {
    "strongs": "H5782",
    "transliteration": "Ur",
    "gloss": "To awake, stir up, rouse",
    "original": "עוּר",
    "lang": "hebrew",
    "file": "H5782.html"
  },
  {
    "strongs": "H5869",
    "transliteration": "Ayin",
    "gloss": "Eye, sight, appearance",
    "original": "עַיִן",
    "lang": "hebrew",
    "file": "H5869.html"
  },
  {
    "strongs": "H5921",
    "transliteration": "Al",
    "gloss": "Upon, over, above, concerning",
    "original": "עַל",
    "lang": "hebrew",
    "file": "H5921.html"
  },
  {
    "strongs": "H5971",
    "transliteration": "Am",
    "gloss": "People, nation, kinfolk",
    "original": "עַם",
    "lang": "hebrew",
    "file": "H5971.html"
  },
  {
    "strongs": "H6030",
    "transliteration": "Anah",
    "gloss": "To answer, respond, testify",
    "original": "עָנָה",
    "lang": "hebrew",
    "file": "H6030.html"
  },
  {
    "strongs": "H6040",
    "transliteration": "Oni",
    "gloss": "Affliction, poverty, misery",
    "original": "עֳנִי",
    "lang": "hebrew",
    "file": "H6040.html"
  },
  {
    "strongs": "H6213",
    "transliteration": "Asah",
    "gloss": "To do, make, accomplish",
    "original": "עָשָׂה",
    "lang": "hebrew",
    "file": "H6213.html"
  },
  {
    "strongs": "H622",
    "transliteration": "ʾāsaph",
    "gloss": "To gather, collect, assemble",
    "original": "אָסַף",
    "lang": "hebrew",
    "file": "H622.html"
  },
  {
    "strongs": "H6310",
    "transliteration": "Peh",
    "gloss": "Mouth, speech, opening",
    "original": "פֶּה",
    "lang": "hebrew",
    "file": "H6310.html"
  },
  {
    "strongs": "H6327",
    "transliteration": "puts",
    "gloss": "To scatter, disperse, shatter",
    "original": "פּוּץ",
    "lang": "hebrew",
    "file": "H6327.html"
  },
  {
    "strongs": "H639",
    "transliteration": "ʾaph",
    "gloss": "Nose, nostril; anger, wrath",
    "original": "אַף",
    "lang": "hebrew",
    "file": "H639.html"
  },
  {
    "strongs": "H6440",
    "transliteration": "Panim",
    "gloss": "Face, presence, before",
    "original": "פָּנִים",
    "lang": "hebrew",
    "file": "H6440.html"
  },
  {
    "strongs": "H6588",
    "transliteration": "pesha",
    "gloss": "transgression, rebellion",
    "original": "פֶּשַׁע",
    "lang": "hebrew",
    "file": "H6588.html"
  },
  {
    "strongs": "H6635",
    "transliteration": "Tsaba",
    "gloss": "Host, army, war, service",
    "original": "צָבָא",
    "lang": "hebrew",
    "file": "H6635.html"
  },
  {
    "strongs": "H6662",
    "transliteration": "tsaddiq",
    "gloss": "righteous, just, lawful",
    "original": "צַדִּיק",
    "lang": "hebrew",
    "file": "H6662.html"
  },
  {
    "strongs": "H6664",
    "transliteration": "Tsedek",
    "gloss": "Righteousness, justice, rightness",
    "original": "צֶדֶק",
    "lang": "hebrew",
    "file": "H6664.html"
  },
  {
    "strongs": "H6666",
    "transliteration": "Tsedaqah",
    "gloss": "Righteousness, righteous deeds",
    "original": "צְדָקָה",
    "lang": "hebrew",
    "file": "H6666.html"
  },
  {
    "strongs": "H6680",
    "transliteration": "Tsavah",
    "gloss": "To command, order, charge",
    "original": "צָוָה",
    "lang": "hebrew",
    "file": "H6680.html"
  },
  {
    "strongs": "H6743",
    "transliteration": "tsalach",
    "gloss": "To prosper, succeed, advance",
    "original": "צָלַח",
    "lang": "hebrew",
    "file": "H6743.html"
  },
  {
    "strongs": "H6817",
    "transliteration": "tsa'aq",
    "gloss": "To cry out, call for help",
    "original": "צָעַק",
    "lang": "hebrew",
    "file": "H6817.html"
  },
  {
    "strongs": "H6918",
    "transliteration": "qadosh",
    "gloss": "holy, sacred, set apart",
    "original": "קָדוֹשׁ",
    "lang": "hebrew",
    "file": "H6918.html"
  },
  {
    "strongs": "H6942",
    "transliteration": "Qadash",
    "gloss": "To consecrate, sanctify, set apart",
    "original": "קָדַשׁ",
    "lang": "hebrew",
    "file": "H6942.html"
  },
  {
    "strongs": "H6960",
    "transliteration": "qavah",
    "gloss": "To wait for, look for, hope",
    "original": "קָוָה",
    "lang": "hebrew",
    "file": "H6960.html"
  },
  {
    "strongs": "H6963",
    "transliteration": "Qol",
    "gloss": "Voice, sound, noise",
    "original": "קוֹל",
    "lang": "hebrew",
    "file": "H6963.html"
  },
  {
    "strongs": "H7069",
    "transliteration": "Qanah",
    "gloss": "To acquire, buy, create",
    "original": "קָנָה",
    "lang": "hebrew",
    "file": "H7069.html"
  },
  {
    "strongs": "H7121",
    "transliteration": "Qara",
    "gloss": "To call, proclaim, read",
    "original": "קָרָא",
    "lang": "hebrew",
    "file": "H7121.html"
  },
  {
    "strongs": "H7200",
    "transliteration": "raah",
    "gloss": "to see, look, perceive",
    "original": "רָאָה",
    "lang": "hebrew",
    "file": "H7200.html"
  },
  {
    "strongs": "H7223",
    "transliteration": "Rishon",
    "gloss": "First, former, beginning",
    "original": "רִאשׁוֹן",
    "lang": "hebrew",
    "file": "H7223.html"
  },
  {
    "strongs": "H7225",
    "transliteration": "reshith",
    "gloss": "Beginning, firstfruits, chief",
    "original": "רֵאשִׁית",
    "lang": "hebrew",
    "file": "H7225.html"
  },
  {
    "strongs": "H7307",
    "transliteration": "Ruach",
    "gloss": "Spirit, wind, breath",
    "original": "רוּחַ",
    "lang": "hebrew",
    "file": "H7307.html"
  },
  {
    "strongs": "H734",
    "transliteration": "ʾōrach",
    "gloss": "Path, way, road",
    "original": "אֹרַח",
    "lang": "hebrew",
    "file": "H734.html"
  },
  {
    "strongs": "H7355",
    "transliteration": "racham",
    "gloss": "To have compassion, show mercy",
    "original": "רָחַם",
    "lang": "hebrew",
    "file": "H7355.html"
  },
  {
    "strongs": "H7451",
    "transliteration": "ra",
    "gloss": "Evil, bad, wicked, harmful",
    "original": "רַע",
    "lang": "hebrew",
    "file": "H7451.html"
  },
  {
    "strongs": "H7462",
    "transliteration": "ra'ah",
    "gloss": "To shepherd, tend, feed, pasture",
    "original": "רָעָה",
    "lang": "hebrew",
    "file": "H7462.html"
  },
  {
    "strongs": "H7489",
    "transliteration": "Raa",
    "gloss": "To be evil, bad, harmful",
    "original": "רָעַע",
    "lang": "hebrew",
    "file": "H7489.html"
  },
  {
    "strongs": "H7563",
    "transliteration": "Rasha",
    "gloss": "Wicked, guilty, criminal",
    "original": "רָשָׁע",
    "lang": "hebrew",
    "file": "H7563.html"
  },
  {
    "strongs": "H7592",
    "transliteration": "Shaal",
    "gloss": "To ask, inquire, request",
    "original": "שָׁאַל",
    "lang": "hebrew",
    "file": "H7592.html"
  },
  {
    "strongs": "H7626",
    "transliteration": "Shebet",
    "gloss": "Tribe, rod, staff, scepter",
    "original": "שֵׁבֶט",
    "lang": "hebrew",
    "file": "H7626.html"
  },
  {
    "strongs": "H7676",
    "transliteration": "Shabbath",
    "gloss": "Sabbath, rest",
    "original": "שַׁבָּת",
    "lang": "hebrew",
    "file": "H7676.html"
  },
  {
    "strongs": "H7725",
    "transliteration": "shub",
    "gloss": "to return, turn back, repent",
    "original": "שׁוּב",
    "lang": "hebrew",
    "file": "H7725.html"
  },
  {
    "strongs": "H776",
    "transliteration": "Eretz",
    "gloss": "Earth, land, country",
    "original": "אֶרֶץ",
    "lang": "hebrew",
    "file": "H776.html"
  },
  {
    "strongs": "H7760",
    "transliteration": "Sum",
    "gloss": "To put, place, set, appoint",
    "original": "שׂוּם",
    "lang": "hebrew",
    "file": "H7760.html"
  },
  {
    "strongs": "H7812",
    "transliteration": "Shachah",
    "gloss": "To bow down, worship, prostrate",
    "original": "שָׁחָה",
    "lang": "hebrew",
    "file": "H7812.html"
  },
  {
    "strongs": "H7860",
    "transliteration": "Shoter",
    "gloss": "Officer, official, foreman",
    "original": "שֹׁטֵר",
    "lang": "hebrew",
    "file": "H7860.html"
  },
  {
    "strongs": "H7892",
    "transliteration": "Shir",
    "gloss": "Song, singing",
    "original": "שִׁיר",
    "lang": "hebrew",
    "file": "H7892.html"
  },
  {
    "strongs": "H7965",
    "transliteration": "shalom",
    "gloss": "peace, completeness, welfare",
    "original": "שָׁלוֹם",
    "lang": "hebrew",
    "file": "H7965.html"
  },
  {
    "strongs": "H7971",
    "transliteration": "Shalach",
    "gloss": "To send, send away, let go",
    "original": "שָׁלַח",
    "lang": "hebrew",
    "file": "H7971.html"
  },
  {
    "strongs": "H7999",
    "transliteration": "Shalam",
    "gloss": "To be complete, make peace, repay",
    "original": "שָׁלַם",
    "lang": "hebrew",
    "file": "H7999.html"
  },
  {
    "strongs": "H802",
    "transliteration": "Ishshah",
    "gloss": "Woman, wife",
    "original": "אִשָּׁה",
    "lang": "hebrew",
    "file": "H802.html"
  },
  {
    "strongs": "H8034",
    "transliteration": "shem",
    "gloss": "Name, renown, fame, reputation",
    "original": "שֵׁם",
    "lang": "hebrew",
    "file": "H8034.html"
  },
  {
    "strongs": "H8055",
    "transliteration": "Samach",
    "gloss": "To rejoice, be glad",
    "original": "שָׂמַח",
    "lang": "hebrew",
    "file": "H8055.html"
  },
  {
    "strongs": "H8057",
    "transliteration": "Simchah",
    "gloss": "Joy, gladness, celebration",
    "original": "שִׂמְחָה",
    "lang": "hebrew",
    "file": "H8057.html"
  },
  {
    "strongs": "H8064",
    "transliteration": "shamayim",
    "gloss": "heavens, sky",
    "original": "שָׁמַיִם",
    "lang": "hebrew",
    "file": "H8064.html"
  },
  {
    "strongs": "H8085",
    "transliteration": "shama",
    "gloss": "to hear, listen, obey",
    "original": "שָׁמַע",
    "lang": "hebrew",
    "file": "H8085.html"
  },
  {
    "strongs": "H8104",
    "transliteration": "Shamar",
    "gloss": "To keep, guard, observe, preserve",
    "original": "שָׁמַר",
    "lang": "hebrew",
    "file": "H8104.html"
  },
  {
    "strongs": "H8199",
    "transliteration": "Shaphat",
    "gloss": "To judge, govern, decide",
    "original": "שָׁפַט",
    "lang": "hebrew",
    "file": "H8199.html"
  },
  {
    "strongs": "H834",
    "transliteration": "Asher",
    "gloss": "Who, which, that",
    "original": "אֲשֶׁר",
    "lang": "hebrew",
    "file": "H834.html"
  },
  {
    "strongs": "H8416",
    "transliteration": "Tehillah",
    "gloss": "Praise, song of praise",
    "original": "תְּהִלָּה",
    "lang": "hebrew",
    "file": "H8416.html"
  },
  {
    "strongs": "H8432",
    "transliteration": "Tavek",
    "gloss": "Midst, middle, among",
    "original": "תָּוֶךְ",
    "lang": "hebrew",
    "file": "H8432.html"
  },
  {
    "strongs": "H8451",
    "transliteration": "torah",
    "gloss": "law, instruction, teaching",
    "original": "תּוֹרָה",
    "lang": "hebrew",
    "file": "H8451.html"
  },
  {
    "strongs": "H8478",
    "transliteration": "Tachath",
    "gloss": "Under, beneath, instead of",
    "original": "תַּחַת",
    "lang": "hebrew",
    "file": "H8478.html"
  },
  {
    "strongs": "H8537",
    "transliteration": "Tom",
    "gloss": "Integrity, completeness, innocence",
    "original": "תֹּם",
    "lang": "hebrew",
    "file": "H8537.html"
  },
  {
    "strongs": "H8549",
    "transliteration": "Tamim",
    "gloss": "Complete, blameless, without defect",
    "original": "תָּמִים",
    "lang": "hebrew",
    "file": "H8549.html"
  },
  {
    "strongs": "H8615",
    "transliteration": "Tikvah",
    "gloss": "Hope, expectation, cord",
    "original": "תִּקְוָה",
    "lang": "hebrew",
    "file": "H8615.html"
  },
  {
    "strongs": "H8643",
    "transliteration": "Teruah",
    "gloss": "Shout, alarm, blast",
    "original": "תְּרוּעָה",
    "lang": "hebrew",
    "file": "H8643.html"
  },
  {
    "strongs": "H935",
    "transliteration": "Bo",
    "gloss": "To come, enter, go in",
    "original": "בּוֹא",
    "lang": "hebrew",
    "file": "H935.html"
  },
  {
    "strongs": "H982",
    "transliteration": "batach",
    "gloss": "to trust, rely on, be confident",
    "original": "בָּטַח",
    "lang": "hebrew",
    "file": "H982.html"
  },
  {
    "strongs": "H996",
    "transliteration": "bêyn",
    "gloss": "Between, among, in the midst of",
    "original": "בֵּין",
    "lang": "hebrew",
    "file": "H996.html"
  }
]